Workbook
Name aa: #REF!
Name Årstal: #REF!
Name asdf: #REF!
Name asdfasfd: #REF!
Name b: #REF!
Name BTV11_15: '[1]arbejds ark LARGE New'!$K$33
Name bvcxx: #REF!
Name bvcxxx: #REF!
Name BVT17_15: '[1]arbejds ark LARGE New'!$S$67
Name d: #REF!
Name ddd: #REF!
Name ddddd: #REF!
Name e: #REF!
Name Elpriser: #REF!
Name emethanol: #REF!
Name EUR__DKK: [2]KeyNH3!$D$34
Name EUR16tilEUR15: '[1]22 Photovoltaics LARGE Old'!$N$2
Name EUR2DKK: #REF!
Name eurusd_rate: [3]Input!$B$7
Name ewr: #REF!
Name f: #REF!
Name fds: #REF!
Name h: #REF!
Name Heat_production_capacity_for_one_unit__kW_h: #REF!
Name Kategorier: #REF!
Name NyMethanol: #REF!
Name nyny: #REF!
Name Oil_ex_single: #REF!
Name qwer: #REF!
Name sadf: #REF!
Name sheet10: #REF!
Name sheet11: #REF!
Name sheet2: #REF!
Name sheet20: #REF!
Name sheet27: #REF!
Name sheet28: #REF!
Name sheet29: #REF!
Name sheet3: '1.1 AEC 1 GW '!$C$1
Name sheet3: #REF!
Name sheet30: #REF!
Name sheet31: #REF!
Name sheet32: #REF!
Name sheet33: #REF!
Name sheet34: #REF!
Name sheet35: #REF!
Name sheet36: #REF!
Name sheet37: #REF!
Name sheet38: #REF!
Name sheet4: #REF!
Name sheet5: #REF!
Name sheet9: #REF!
Name Start1: #REF!
Name Start10: #REF!
Name Start11: #REF!
Name Start12: '[4]5.7 Vegetable oil FAME'!#REF!
Name Start13: '[4]5.8 UCO & animal fat FAME'!#REF!
Name Start14: '[4]5.10 Hydrogenated veg oil'!#REF!
Name Start15: '[4]5.9 HVO jet fuel'!#REF!
Name Start16: '[4]5.11 1st generation ethanol'!#REF!
Name Start17: '[4]3.1 Pyrolysis oils'!#REF!

Sheet Intro
A8: Data from Added value data
A9: Input values
A10: Needs to dobble check
A11: Changes maded - Pedro

Sheet Cockpit
A1: Heat pump - 1 | B1: HP_Values_1 | C1: Uites | D1: Heat pump - 2 | E1: HP_Values_2 | F1: Uites | G1: Electrical boiler | H1: EB_Values | J1: Boiler Natural gas | K1: NG_Values | M1: Boiler waste | N1: WTE_Values | P1: Boiler biomass - straw | Q1: Straw_Values | S1: Boiler biomass - Træflis | T1: Woodchips_Values | V1: Boiler biomass - biooile | W1: biooile_Values | Y1: CHP - Waste to energy | Z1: CHP_Values | AB1: Solar panel | AC1: SP_Values | AD1: Uites | AE1: PtX electrolyser - MorGen ACE | AF1: PtH2_1 | AI1: PtX electrolyser - HØST | AJ1: PtH2_2 | AL1: Thermal Storage | AM1: TS_Values | AO1: District heating inputs | AP1: DH_Values | AQ1: Uites | AR1: General system inputs | AS1: General_Values | AT1: Uites | AU1: District Cooling inputs | AV1: DC_Values | AW1: Uites | AX1: Solar panel | AY1: SP_Values | AZ1: Uites
A2: COP | B2: 3 | C2: Nan | D2: COP | E2: 0 | F2: Nan | G2: Efficiancy | H2: 0.99 | I2: % | J2: Efficiancy | K2: 0.8 | L2: % | M2: Efficiancy | N2: 0.8 | O2: % | P2: Efficiancy | Q2: 0.8 | R2: % | S2: Efficiancy | T2: 0.8 | U2: % | V2: Efficiancy | W2: 0.8 | X2: % | Y2: Minimum capacity of power | Z2: 0 | AA2: MW | AB2: Efficiancy | AC2: 0.8 | AD2: Nan | AE2: Efficiancy to H2 | AF2: ='1.1 AEC 1 GW '!C10/100 -> 0.52341783 | AG2: % | AH2: 1 | AI2: Efficiancy to H2 | AJ2: ='1.1 PEMEC 1 GW'!C14/100 -> 0.5258481 | AK2: % | AL2: Mass | AM2: 40000 | AN2: Liters | AO2: DH return temperature | AP2: 40 | AQ2: Degress C | AR2: Emission cost CO2 | AS2: ='emission cost'!$C$14/1000 -> 0.70152 | AT2: kr/kg | AU2: DC Ambiant cooling temperature | AV2: 25 | AW2: Degress C | AX2: Efficiancy | AY2: 0.8 | AZ2: Nan
A3: Minimum capacity of power | B3: 0 | C3: MW | D3: Minimum capacity of power | E3: =B3 -> 0 | F3: MW | G3: Minimum capacity of power | H3: 0 | I3: MW | J3: Mass flow rate min | K3: 0 | L3: Kg/s | M3: Mass flow rate min | N3: 0 | O3: MJ/s | P3: Mass flow rate min | Q3: 0 | R3: kJ/s | S3: Mass flow rate min | T3: 0 | U3: Kg/s | V3: Mass flow rate min | W3: 0 | X3: Kg/s | Y3: Maximum capacity of power | Z3: 65 | AA3: MW | AB3: Minimum capacity of power | AC3: 0 | AD3: MW | AE3: Efficiancy to Heat | AF3: ='1.1 AEC 1 GW '!C18/100 -> 0.27618663 | AG3: % | AH3: 2 | AI3: Efficiancy to Heat | AJ3: ='1.1 PEMEC 1 GW'!C18/100 -> 0.33586067 | AK3: % | AL3: Specif heat capacity | AM3: 4.185 | AN3: kJ/kg*K | AO3: DH forward temperature | AP3: 90 | AQ3: Degress C | AR3: Emission cost Nox | AS3: ='emission cost'!$D$2 -> 12 | AT3: kr./kg | AU3: Efficiancy of the cooling system | AV3: 3 | AW3: Corrosponding to a COP or EER | AX3: Minimum capacity of power | AY3: 0 | AZ3: MW
A4: Maximum capacity of power | B4: 20.5 | C4: MW | D4: Maximum capacity of power | E4: 0 | F4: MW | G4: Maximum capacity of power | H4: 40 | I4: MW | J4: Mass flow rate max | K4: =K6/(K2*K8) -> 1.5095339 | L4: Kg/s | M4: Mass flow rate max | N4: =N6/(N2*N8) -> 1.3812155 | O4: MJ/s | P4: Mass flow rate max | Q4: =Q6/(Q2*Q8) -> 0.25862069 | R4: MJ/s | S4: Mass flow rate max | T4: =T6/(T2*T8) -> 8.172043 | U4: Kg/s | V4: Mass flow rate max | W4: =W6/(W2*W8) -> 2.9550827 | X4: Kg/s | Y4: Minimum production capacity of power | Z4: 0.35095385 | AA4: % of max capacity | AB4: Maximum capacity of power | AC4: 5 | AD4: MW | AE4: Minimum capacity of power | AF4: 0 | AG4: MW | AH4: 3 | AI4: Minimum capacity of power | AJ4: 0 | AK4: MW | AL4: Temperature max | AM4: 90 | AN4: C | AO4: Max flow to DH | AP4: =(Z24+T24+K24+H24)/(AS8*(AP3-AP5)) -> 876.14496 | AQ4: kg/s | AR4: Emission cost Sox | AS4: ='emission cost'!$C$2 -> 13 | AT4: kr./kg | AU4: Chiller min capacity | AV4: 0 | AX4: Maximum capacity of power | AY4: 5 | AZ4: MW
A5: Base Load | B5: 6.56 | C5: MW | D5: Minimum capacity of power | E5: 0 | F5: MW | G5: Base Load | H5: 0.8 | I5: MW | J5: Minimum capacity of heat | K5: 0 | L5: MW | M5: Minimum capacity of heat | N5: 0 | O5: MW | P5: Minimum capacity of heat | Q5: 0 | R5: MW | S5: Minimum capacity of heat | T5: 0 | U5: MW | V5: Minimum capacity of heat | W5: 0 | X5: MW | Y5: Minimum capacity of heat | Z5: 0 | AA5: MW | AB5: Cross area | AC5: 50 | AD5: m^2 | AE5: Maximum capacity of power | AF5: 1000 | AG5: MW | AH5: 4 | AI5: Maximum capacity of power | AJ5: 1000 | AK5: MW | AL5: Temperature min | AM5: 40 | AN5: C | AO5: Max excess hear temp DH | AP5: 60 | AQ5: =AJ23 -> 60 | AR5: Emission cost CO2 Affald | AS5: ='emission cost'!B17/1000 -> 0.1957 | AT5: kr./kg | AU5: Chiller Max capacity power | AV5: =AF3*AF5+100 -> 376.18663 | AW5: MW | AX5: Cross area | AY5: 50 | AZ5: m^2 | BA5: =(AJ5*AJ3)+AF3*AF5+100 -> 712.04731
A6: Emissionfactor CO2 | B6: =Emissionsfactor!C37 -> 41 | C6: kg/ MWh | D6: Emissionfactor CO2 | E6: =B6 -> 41 | F6: kg/ MWh | G6: Emissionfactor CO2 | H6: =E6 -> 41 | I6: kg/ MWh | J6: Maximum capacity of heat | K6: 57 | L6: MW | M6: Maximum capacity of heat | N6: 10 | O6: MW | P6: Maximum capacity of heat | Q6: 3 | R6: MW | S6: Maximum capacity of heat | T6: 60.8 | U6: MW | V6: Maximum capacity of heat | W6: 100 | X6: MW | Y6: Maximum capacity of heat | Z6: 87.765 | AA6: MW | AB6: OPEX variable - should be cost of electricity | AC6: =0.19*References!$B$17 -> 1.4174 | AD6: DKK/MWh | AE6: Minimum production capacity of power | AF6: 0.1 | AG6: % of max capacity | AH6: 5 | AI6: Minimum production capacity of power | AJ6: 0.1 | AK6: % of max capacity | AL6: Minium thermal capacity | AM6: 0.1 | AN6: of Heat capacity | AO6: Max flow to DH from PtX | AP6: 1051.374 | AQ6: kg/s | AR6: Emission cost NOx Affald | AS6: ='emission cost'!C33 -> 5.3 | AT6: kr./kg | AU6: Cooling price | AV6: 60 | AW6: DKK/MWh | AX6: OPEX variable - should be cost of electricity | AY6: =0.19*References!$B$17 -> 1.4174 | AZ6: DKK/MWh | BA6: var 40 før
A7: Emissionfactor NOx | B7: =Emissionsfactor!G37/1000 -> 0.0019 | C7: kg/ MWh | D7: Emissionfactor NOx | E7: =B7 -> 0.0019 | F7: kg/ MWh | G7: Emissionfactor NOx | H7: =E7 -> 0.0019 | I7: kg/ MWh | J7: Minimum production capacity of heat | K7: 9.7 | L7: MW | M7: Minimum production capacity of heat | N7: 0 | O7: % of max capacity | P7: Minimum production capacity of heat | Q7: 0.1 | R7: % of max capacity | S7: Minimum production capacity of heat | T7: 21.3 | U7: MW | V7: Minimum production capacity of heat | W7: 10 | X7: MW | Y7: Minimum production capacity of heat | Z7: 42 | AA7: MW | AB7: OPEX fixed | AC7: =0.09*References!$B$17 -> 0.6714 | AD7: DKK/MWh/year | AE7: Emissionfactor CO2 | AF7: =Emissionsfactor!$C$37 -> 41 | AG7: kg/MWh | AH7: 6 | AI7: Emissionfactor CO2 | AJ7: =Emissionsfactor!$C$37 -> 41 | AK7: kg/MWh | AR7: Emission cost CO2 Affald | AT7: kr./kg | AU7: Delta temperature to the ambiant | AV7: 10 | AW7: Degress C | AX7: OPEX fixed | AY7: =0.09*References!$B$17 -> 0.6714 | AZ7: DKK/MWh/year
A8: Emissionfactor SOx | B8: =Emissionsfactor!K37/1000 -> 0.177 | C8: kg/ MWh | D8: Emissionfactor SOx | E8: =B8 -> 0.177 | F8: kg/ MWh | G8: Emissionfactor SOx | H8: =E8 -> 0.177 | I8: kg/ MWh | J8: LHV | K8: ='Heat value'!B16 -> 47.2 | L8: MJ/kg | M8: LHV | N8: ='Heat value'!C20 -> 9.05 | O8: MJ/kg | P8: LHV | Q8: ='Heat value'!B25 -> 14.5 | R8: MJ/kg | S8: LHV | T8: ='Heat value'!B26 -> 9.3 | U8: MJ/kg | V8: LHV | W8: ='Heat value'!B12 -> 42.3 | X8: MJ/kg | Y8: CM value | Z8: 0.4 | AE8: Emissionfactor NOx | AF8: =Emissionsfactor!G37/1000 -> 0.0019 | AG8: kg/ GJ | AH8: 7 | AI8: Emissionfactor NOx | AJ8: =Emissionsfactor!G37/1000 -> 0.0019 | AK8: kg/ GJ | AR8: Water CP | AS8: =4.185/1000 -> 0.004185 | AT8: MJ/kg*K | AU8: Cooling capacity | AV8: =AV5-100 -> 276.18663 | AW8: MJ/s
A9: Start up cost | B9: 2500 | C9: DKK | D9: Fuel cost | E9: electricity price | F9: DKK/MWh | G9: Start up cost | H9: 150 | I9: DKK | J9: Emissionfactor CO2 | K9: =Emissionsfactor!B74/1000 -> 0.05547 | L9: kg/ MJ | M9: Emissionfactor CO2 | N9: =Emissionsfactor!C15 -> 42.5 | O9: kg/ GJ | P9: Emissionfactor CO2 | Q9: =Emissionsfactor!C19 -> 0 | R9: kg/ GJ | S9: Emissionfactor CO2 | T9: 0 | U9: kg/ MJ | V9: Emissionfactor CO2 | W9: =Emissionsfactor!C5/1000 -> 0 | X9: kg/ MJ | Y9: Ramping up and down | Z9: 0.3 | AA9: % of power production | AE9: Emissionfactor SOx | AF9: =Emissionsfactor!K37/1000 -> 0.177 | AG9: kg/ GJ | AH9: 8 | AI9: Emissionfactor SOx | AJ9: =Emissionsfactor!K37/1000 -> 0.177 | AK9: kg/ GJ | AU9: OPEX Var | AV9: 1 | AW9: [DKK/MWh]
A10: OPEX_Variable | B10: 8 | C10: kr/MWh | D10: Start up cost | E10: =B9 -> 2500 | F10: DKK | G10: OPEX_Variable | H10: 4.2 | I10: kr/MWh | J10: Emissionfactor NOx | K10: =Emissionsfactor!G18/10^6 -> 3.17e-05 | L10: kg/ MJ | M10: Emissionfactor NOx | N10: =Emissionsfactor!G15/1000 -> 0.079 | O10: kg/ GJ | P10: Emissionfactor NOx | Q10: =Emissionsfactor!G19/1000 -> 0.09 | R10: kg/ GJ | S10: Emissionfactor NOx | T10: =Emissionsfactor!G21/10^6 -> 9e-05 | U10: kg/ MJ | V10: Emissionfactor NOx | W10: =Emissionsfactor!G5/1000 -> 0.08 | X10: kg/ MJ | Y10: LHV | Z10: ='Heat value'!D20 -> 10.7 | AA10: MJ/kg | AE10: Max flow | AF10: =(AF5*AF3)/($AS$8*(AF23-AF24)) -> 2199.8139 | AG10: kg/s | AH10: 9 | AI10: Max flow | AJ10: =(AJ5*AJ3)/($AS$8*(AJ23-AJ24)) -> 2675.1149 | AK10: m/s
A11: Fuel cost | B11: electricity price | C11: DKK/MWh | D11: OPEX_Variable | E11: 8 | F11: kr/MWh | G11: Fuel cost | H11: electricity price | I11: DKK/MWh | J11: Emissionfactor SOx | K11: =Emissionsfactor!F18/10^6 -> 4e-07 | L11: kg/ MJ | M11: Emissionfactor SOx | N11: =Emissionsfactor!F15/1000 -> 0.0083 | O11: kg/ GJ | P11: Emissionfactor SOx | Q11: =Emissionsfactor!F19/1000 -> 0.115 | R11: kg/ GJ | S11: Emissionfactor SOx | T11: =Emissionsfactor!F21/10^6 -> 1.1e-05 | U11: kg/ MJ | V11: Emissionfactor SOx | W11: =Emissionsfactor!F5/1000 -> 0.011 | X11: kg/ MJ | Y11: Emissionfactor CO2 | Z11: =Emissionsfactor!B86/1000 * (1-Emissionsfactor!D86) -> 0.04249986 | AA11: kg/ MJ | AE11: min flow | AF11: 0 | AG11: m/s | AH11: 10 | AI11: min flow | AJ11: 0 | AK11: m/s
M12: Emission cost CO2 | N12: ='emission cost'!$C$14/1000 -> 0.70152 | O12: Kr./ton | P12: Emission cost CO2 | Q12: ='emission cost'!$C$14*1000 -> 701520 | R12: Kr./kg | Y12: Emissionfactor NOx | Z12: =Emissionsfactor!G15/10^6 -> 7.9e-05 | AA12: kg/ MJ | AE12: Fuel cost | AF12: electricity price | AG12: DKK/MWh | AH12: 11 | AI12: Fuel cost | AJ12: electricity price | AK12: DKK/MWh
M13: Emission cost Nox | N13: ='emission cost'!$D$2 -> 12 | O13: kr./kg | P13: Emission cost Nox | Q13: ='emission cost'!$D$2 -> 12 | R13: kr./kg | Y13: Emissionfactor SOx | Z13: =Emissionsfactor!F15/10^6 -> 8.3e-06 | AA13: kg/ MJ | AE13: Life time left | AF13: 10 | AG13: years | AH13: 12 | AI13: Life time left | AJ13: 10 | AK13: years
M14: Emission cost Sox | N14: ='emission cost'!$C$2 -> 13 | O14: kr./kg | P14: Emission cost Sox | Q14: ='emission cost'!$C$2 -> 13 | R14: kr./kg | Y14: Fuel cost | Z14: 365 | AA14: kr./tons | AE14: Present value of the plant | AF14: 10000 | AG14: DKK | AH14: 13 | AI14: Present value of the plant | AJ14: 10000 | AK14: DKK | AR14: WTE operation | AS14: TRUE
J15: Fuel cost | K15: ='Fuel cost'!B7 -> 238.24 | L15: kr./GJ | M15: Fuel cost | N15: ='Fuel cost'!B49 -> 484 | O15: kr./ton | P15: Fuel cost | Q15: ='Fuel cost'!B23 -> 57.78 | R15: kr./GJ | S15: Fuel cost | T15: ='Fuel cost'!B24 -> 67.91 | U15: kr./GJ | V15: Fuel cost | W15: ='Fuel cost'!B5 -> 95.84 | X15: kr./GJ | Y15: OPEX_varable | Z15: 76 | AA15: kr/MWh | AE15: OPEX variable | AF15: =0.09*References!B17 -> 0.6714 | AG15: DKK/kg | AH15: 14 | AI15: OPEX | AJ15: =AF15 -> 0.6714 | AK15: % of CAPEX | AR15: WTE operation | AS15: FALSE
M16: Life time left | N16: 10 | O16: years | P16: Life time left | Q16: 10 | R16: years | Y16: Start up cost | Z16: 200000 | AA16: DKK | AE16: Revenue H2 | AF16: ='Fuel cost'!B53*References!B17 -> 37.3 | AG16: Kr/kg | AH16: 15 | AI16: Revenue H2 | AJ16: ='Fuel cost'!B53*References!B17 -> 37.3 | AK16: Kr/kg
M17: Present value of the plant | N17: 10000 | O17: DKK | P17: Present value of the plant | Q17: 10000 | R17: DKK | Y17: Efficiancy | Z17: 0.9 | AA17: % | AE17: Revenue excess heat | AF17: 180 | AG17: kr/MWh | AH17: 16 | AI17: Revenue excess heat | AJ17: =AF17 -> 180 | AK17: kr/MWh
J18: OPEX_Variable | K18: 41.7 | L18: kr/MWh | M18: OPEX | N18: 0.05 | O18: % of CAPEX | P18: OPEX | Q18: 0.05 | R18: % of CAPEX | S18: OPEX_Variable | T18: 19.3 | U18: kr/MWh | V18: OPEX_Variable | W18: 5 | X18: kr/MWh | Y18: Force or not | Z18: TRUE | AE18: Cooling cost | AF18: 60 | AG18: kr/MWh | AH18: 17 | AI18: Cooling cost | AJ18: 50 | AK18: kr/MWh
J19: Start up cost | K19: 2500 | L19: DKK | M19: Start up cost | N19: 100000 | O19: DKK | P19: Start up cost | Q19: 100000 | R19: DKK | S19: Start up cost | T19: 100000 | U19: DKK | V19: Start up cost | W19: 1500 | X19: DKK | Y19: C_lower value | Z19: ='CHP - Calculation'!G24 -> -0.14314286 | AE19: converting from kg H2 / Electricity consumption | AF19: ='1.1 AEC 1 GW '!C19 -> 19.105195 | AG19: [stack level, KgH2/MWh - e] | AH19: 18 | AI19: converting from Electricity consumption / kh H2 | AJ19: ='1.1 PEMEC 1 GW'!C19 -> 17.752661 | AK19: [stack level, KgH2/MWh - e]
J20: Ramping up and down | K20: 0.2 | L20: % of production | M20: Ramping up and down | N20: 1 | O20: % of production | P20: Ramping up and down | Q20: 0.2 | R20: % of production | S20: Ramping up and down | T20: 0.2 | U20: % of production | V20: Ramping up and down | W20: 0.2 | X20: % of production | Y20: Service start day | Z20: 1 | AA20: Day | AE20: Start up cost | AF20: =1000*References!B17 -> 7460 | AG20: DKK | AH20: 19 | AI20: Start up cost | AJ20: =4*References!B17 -> 29.84 | AK20: DKK
M21: Force or not | N21: False | Y21: Service end day | Z21: 21 | AA21: Day | AE21: Ramping up and down | AF21: ='1.1 AEC 1 GW '!D49 -> 0.75 | AG21: % of production | AH21: 20 | AI21: Ramping up and down | AJ21: ='1.1 PEMEC 1 GW'!D48 -> 1 | AK21: % of production
Y22: Service start Month | Z22: 6 | AA22: Month | AE22: Tariffs DSO(A-høj) + TSO | AF22: ='Fuel cost'!B58 -> 72.99 | AG22: Kr/MWh | AH22: 21
Y23: Service end Month | Z23: 6 | AA23: Month | AE23: Excess heat Temperature | AF23: 60 | AG23: Degress C | AH23: 22 | AI23: Excess heat Temperature | AJ23: 60 | AK23: Degress C
G24: Booster Capacity | H24: 20 | I24: MW | J24: Booster Capacity | K24: 20 | L24: MW | S24: Booster Capacity | T24: 50 | U24: MW | Y24: Booster Capacity | Z24: 20 | AA24: MW | AE24: Cooling Temperature | AF24: 30 | AG24: Degress C | AH24: 23 | AI24: Cooling Temperature | AJ24: 30 | AK24: Degress C

Sheet CHP - Calculation
D4: Inputs cells
D5: Calculated cells
D6: Equal to reference cell
B7: We want to findthe Cv value | D7: Cv eqaution
D8: Cv eqaution | F8: When P = to P_max then Q is equal to 0 | G8: Is unknown in this regards, as we want to calculate it to find the cross section between the lines, as we know the Cm value
D9: P(Q) = Cv * Q + P_max | E9: P_max | F9: Q | G9: Cv
E10: =Cockpit!Z3 -> 65 | F10: 0 | G10: =(E10-E16)/(F10-F16) -> -0.36085684 | H10: This one should be between -0,5 and -0,3
D13: Cm equation
D14: Cm equation | E14: We can calcualte this based on the equation | F14: We want to find the cross section when Q is equal to Q_max, as we know Q_maxa
D15: P(Q) =Q * CM | E15: P | F15: Q_max | G15: Cm
E16: =F16*G16 -> 34.172 | F16: 85.43 | G16: =Cockpit!Z8 -> 0.4 | H16: Small equal to 0,4 big to 0,6
E18: X | F18: Y
D19: So the two equations cross in (x,y) | E19: =F16 -> 85.43 | F19: =E16 -> 34.172
B21: We want to find the cross section between Cm and Cv_small equation | D21: Cv eqaution
D22: Cv_small eqaution | F22: When P = to P_min then Q is equal to 0 | G22: Is unknown in this regards, as we want to calculate it to find the cross section between the lines, as we know the Cm value
D23: P(Q) = Cv * Q + P | E23: P_min | F23: Q | G23: C_lower_value
E24: =Cockpit!Z4*Cockpit!Z3 -> 22.812 | F24: 0 | G24: =(E24-F33)/(F24-E33) -> -0.14314286 | H24: This one should be between -0,5 and -0,3
D27: Cm equation
D28: Cm equation | E28: We can calcualte this based on the equation | F28: We want to find the cross section when Q is equal to Q_min - we do that by setting the two equations equal to each other
D29: P(Q) =Q * CM | E29: P | F29: Q_min | G29: Cm
E30: =F30*G30 -> 16.8 | F30: =Cockpit!Z7 -> 42 | G30: =G16 -> 0.4 | H30: Small equal to 0,4 big to 0,6
E32: X | F32: Y
D33: So the two equations cross in (x,y) | E33: =F30 -> 42 | F33: =E30 -> 16.8

Sheet References
A1: Sheet | B1: datatable | C1: Reference | D1: Link
A2: Electricity price 2024 | C2: Energinets fremskrivninger | D2: energinets-elpriser-af22-maj-2023 | E2: done
A3: Heat value | C3: ENS - Standart forudsætninger | D3: https://syddanskuni-my.sharepoint.com/personal/busterhansen_sdu_dk/Documents/Sector%20coupling/Literature/heat%20value/standardforudsaetninger_24-11-21.pdf | E3: DONE
A4: Emissionsfactor | B4: CO2, NOx, Sox in grid and fuels | C4: SØB | D4: https://syddanskuni-my.sharepoint.com/personal/busterhansen_sdu_dk/Documents/Sector%20coupling/Literature/CO2-emission%20factor/soeb22.pdf | E4: done
B5: CO2 in fuels | C5: ENS - standart faktor | D5: https://syddanskuni-my.sharepoint.com/personal/busterhansen_sdu_dk/Documents/Sector%20coupling/Literature/CO2-emission%20factor/energistyrelsens_standardfaktorer_for_2021-25-01-2022.pdf
A6: Emission cost | B6: NOx, SOx Cost | C6: SØB | D6: https://syddanskuni-my.sharepoint.com/personal/busterhansen_sdu_dk/Documents/Sector%20coupling/Literature/CO2-emission%20factor/soeb22.pdf | E6: done
B7: CO2 cost | C7: affald | D7: https://www.pwc.dk/da/afgiftsvejledningen/godtgorelse-satser.html#bilag-6 | E7: DONE
A9: Fuel cost | C9: ENS - Analyse fremskrivninger | D9: af23_-_offentligt_datasaet | E9: done
A10: Cockpit | B10: Cost of h2 | C10: Cost of h2 | D10: af23_-_offentligt_datasaet The European hydrogen market landscape November 2024 - chrome-extension://efaidnbmnnnibpcajpcglclefindmkaj/https://observatory.clean-hydrogen.europa.eu/sites/default/files/2024-11/The%20European%20hydrogen%20market%20landscape_November%202024.pdf | E10: done
A11: Cockpit / AEC | B11: kg H2/kWh | C11: ENS teknology kataloget | E11: done
A17: EuR to DKK | B17: 7.46
B22: CO2 cost - kvotepriser | C22: ENS - Analyse fremskrivninger | D22: https://syddanskuni-my.sharepoint.com/personal/busterhansen_sdu_dk/Documents/Sector%20coupling/Literature/dataset/af23_-_offentligt_datasaet.xlsx
A23: Grid loss | C23: SØB | D23: https://syddanskuni-my.sharepoint.com/personal/busterhansen_sdu_dk/Documents/Sector%20coupling/Literature/CO2-emission%20factor/soeb22.pdf | E23: lige meget
A24: DNI / GHI | B24: Solar data | C24: NSRDB: National Solar Radiation Database | D24: https://nsrdb.nrel.gov/data-viewer | E24: lige meget
D32: #Emi

Sheet Heat value
B1: MJ/kg | E1: GJ/ton | H1: MWh/kg
A2: Brændselstype | B2: Low | C2: avg. | D2: high | E2: Low | F2: avg. | G2: high | H2: Low | I2: avg. | J2: high
A3: Koks | B3: 28.5 | C3: =IF(D3>0,(B3+D3)/2,0) -> 0 | D3: 0 | E3: =B3/1000 -> 0.0285 | F3: =C3/1000 -> 0 | G3: =D3/1000 -> 0 | H3: 0.00792 | I3: =IF(J3>0,(H3+J3)/2,0) -> 0
A4: Stenkul | B4: 17.2 | C4: =IF(D4>0,(B4+D4)/2,0) -> 23.95 | D4: 30.7 | E4: =B4/1000 -> 0.0172 | F4: =C4/1000 -> 0.02395 | G4: =D4/1000 -> 0.0307 | H4: 0.00478 | I4: =IF(J4>0,(H4+J4)/2,0) -> 4.26739 | J4: 8.53
A5: Brunkulsbriketter | B5: 20 | C5: =IF(D5>0,(B5+D5)/2,0) -> 0 | D5: 0 | E5: =B5/1000 -> 0.02 | F5: =C5/1000 -> 0 | G5: =D5/1000 -> 0 | H5: 0.00556 | I5: =IF(J5>0,(H5+J5)/2,0) -> 0
A6: Brunkul med høj brændværdi | B6: 10.5 | C6: =IF(D6>0,(B6+D6)/2,0) -> 15.75 | D6: 21 | E6: =B6/1000 -> 0.0105 | F6: =C6/1000 -> 0.01575 | G6: =D6/1000 -> 0.021 | H6: 0.00292 | I6: =IF(J6>0,(H6+J6)/2,0) -> 2.91646 | J6: 5.83
A7: Brunkul | B7: 5.6 | C7: =IF(D7>0,(B7+D7)/2,0) -> 8.05 | D7: 10.5 | E7: =B7/1000 -> 0.0056 | F7: =C7/1000 -> 0.00805 | G7: =D7/1000 -> 0.0105 | H7: 0.00156 | I7: =IF(J7>0,(H7+J7)/2,0) -> 1.46078 | J7: 2.92
A8: Olieskifer | B8: 8 | C8: =IF(D8>0,(B8+D8)/2,0) -> 8.5 | D8: 9 | E8: =B8/1000 -> 0.008 | F8: =C8/1000 -> 0.0085 | G8: =D8/1000 -> 0.009 | H8: 0.00222 | I8: =IF(J8>0,(H8+J8)/2,0) -> 1.25111 | J8: 2.5
A9: Tørv | B9: 7.8 | C9: =IF(D9>0,(B9+D9)/2,0) -> 10.8 | D9: 13.8 | E9: =B9/1000 -> 0.0078 | F9: =C9/1000 -> 0.0108 | G9: =D9/1000 -> 0.0138 | H9: 0.00217 | I9: =IF(J9>0,(H9+J9)/2,0) -> 1.916085 | J9: 3.83
A10: Tørvebriketter | B10: 16 | C10: =IF(D10>0,(B10+D10)/2,0) -> 16.4 | D10: 16.8 | E10: =B10/1000 -> 0.016 | F10: =C10/1000 -> 0.0164 | G10: =D10/1000 -> 0.0168 | H10: 0.00444 | I10: =IF(J10>0,(H10+J10)/2,0) -> 2.33722 | J10: 4.67
A11: Rest brændselsolie (svær olie) | B11: 40 | C11: =IF(D11>0,(B11+D11)/2,0) -> 0 | D11: 0 | E11: =B11/1000 -> 0.04 | F11: =C11/1000 -> 0 | G11: =D11/1000 -> 0 | H11: 0.01111 | I11: =IF(J11>0,(H11+J11)/2,0) -> 0
A12: Let brændselsolie | B12: 42.3 | C12: =IF(D12>0,(B12+D12)/2,0) -> 0 | D12: 0 | E12: =B12/1000 -> 0.0423 | F12: =C12/1000 -> 0 | G12: =D12/1000 -> 0 | H12: 0.01175 | I12: =IF(J12>0,(H12+J12)/2,0) -> 0
A13: Motorbrændstof (benzin) | B13: 44 | C13: =IF(D13>0,(B13+D13)/2,0) -> 0 | D13: 0 | E13: =B13/1000 -> 0.044 | F13: =C13/1000 -> 0 | G13: =D13/1000 -> 0 | H13: 0.01222 | I13: =IF(J13>0,(H13+J13)/2,0) -> 0
A14: Paraffinolie | B14: 40 | C14: =IF(D14>0,(B14+D14)/2,0) -> 0 | D14: 0 | E14: =B14/1000 -> 0.04 | F14: =C14/1000 -> 0 | G14: =D14/1000 -> 0 | H14: 0.01111 | I14: =IF(J14>0,(H14+J14)/2,0) -> 0
A15: LPG | B15: 46 | C15: =IF(D15>0,(B15+D15)/2,0) -> 0 | D15: 0 | E15: =B15/1000 -> 0.046 | F15: =C15/1000 -> 0 | G15: =D15/1000 -> 0 | H15: 0.01278 | I15: =IF(J15>0,(H15+J15)/2,0) -> 0
A16: Naturgas | B16: 47.2 | C16: =IF(D16>0,(B16+D16)/2,0) -> 0 | D16: 0 | E16: =B16/1000 -> 0.0472 | F16: =C16/1000 -> 0 | G16: =D16/1000 -> 0 | H16: 0.01311 | I16: =IF(J16>0,(H16+J16)/2,0) -> 0
A17: LNG | B17: 45.19 | C17: =IF(D17>0,(B17+D17)/2,0) -> 0 | D17: 0 | E17: =B17/1000 -> 0.04519 | F17: =C17/1000 -> 0 | G17: =D17/1000 -> 0 | H17: 0.01255 | I17: =IF(J17>0,(H17+J17)/2,0) -> 0
A18: Træ (25 % fugtighed) | B18: 13.8 | C18: =IF(D18>0,(B18+D18)/2,0) -> 0 | D18: 0 | E18: =B18/1000 -> 0.0138 | F18: =C18/1000 -> 0 | G18: =D18/1000 -> 0 | H18: 0.00383 | I18: =IF(J18>0,(H18+J18)/2,0) -> 0
A19: Pelllets/ træbriketter | B19: 16.8 | C19: =IF(D19>0,(B19+D19)/2,0) -> 0 | D19: 0 | E19: =B19/1000 -> 0.0168 | F19: =C19/1000 -> 0 | G19: =D19/1000 -> 0 | H19: 0.00467 | I19: =IF(J19>0,(H19+J19)/2,0) -> 0
A20: Affald | B20: 7.4 | C20: =IF(D20>0,(B20+D20)/2,0) -> 9.05 | D20: 10.7 | E20: =B20/1000 -> 0.0074 | F20: =C20/1000 -> 0.00905 | G20: =D20/1000 -> 0.0107 | H20: 0.00206 | I20: =IF(J20>0,(H20+J20)/2,0) -> 1.48603 | J20: 2.97
A21: 1 MJ udvundet varme | B21: 1 | C21: =IF(D21>0,(B21+D21)/2,0) -> 0 | D21: 0 | E21: =B21/1000 -> 0.001 | F21: =C21/1000 -> 0 | G21: =D21/1000 -> 0 | H21: 0.00028 | I21: =IF(J21>0,(H21+J21)/2,0) -> 0
A22: 1 kWh elektrisk energi | B22: 3.6 | C22: =IF(D22>0,(B22+D22)/2,0) -> 0 | D22: 0 | E22: =B22/1000 -> 0.0036 | F22: =C22/1000 -> 0 | G22: =D22/1000 -> 0 | H22: 0.001 | I22: =IF(J22>0,(H22+J22)/2,0) -> 0
A23: Petroleum* | B23: 43.5 | C23: =IF(D23>0,(B23+D23)/2,0) -> 0 | D23: 0 | E23: =B23/1000 -> 0.0435 | F23: =C23/1000 -> 0 | G23: =D23/1000 -> 0 | H23: 0.01208 | I23: =IF(J23>0,(H23+J23)/2,0) -> 0
A24: Petroleumskoks* | B24: 31.4 | C24: =IF(D24>0,(B24+D24)/2,0) -> 0 | D24: 0 | E24: =B24/1000 -> 0.0314 | F24: =C24/1000 -> 0 | G24: =D24/1000 -> 0 | H24: 0.00872 | I24: =IF(J24>0,(H24+J24)/2,0) -> 0
A25: Halm* | B25: 14.5 | C25: =IF(D25>0,(B25+D25)/2,0) -> 0 | D25: 0 | E25: =B25/1000 -> 0.0145 | F25: =C25/1000 -> 0 | G25: =D25/1000 -> 0 | H25: 0.00403 | I25: =IF(J25>0,(H25+J25)/2,0) -> 0
A26: Skovflis* | B26: 9.3 | C26: =IF(D26>0,(B26+D26)/2,0) -> 0 | D26: 0 | E26: =B26/1000 -> 0.0093 | F26: =C26/1000 -> 0 | G26: =D26/1000 -> 0 | H26: 0.00258 | I26: =IF(J26>0,(H26+J26)/2,0) -> 0
A27: Træpiller* | B27: 17.5 | C27: =IF(D27>0,(B27+D27)/2,0) -> 0 | D27: 0 | E27: =B27/1000 -> 0.0175 | F27: =C27/1000 -> 0 | G27: =D27/1000 -> 0 | H27: 0.00486 | I27: =IF(J27>0,(H27+J27)/2,0) -> 0
A28: Træaffald* | B28: 14.7 | C28: =IF(D28>0,(B28+D28)/2,0) -> 0 | D28: 0 | E28: =B28/1000 -> 0.0147 | F28: =C28/1000 -> 0 | G28: =D28/1000 -> 0 | H28: 0.00408 | I28: =IF(J28>0,(H28+J28)/2,0) -> 0

Sheet Emissionsfactor
A1: Brændsel | B1: Anlægstype | C1: CO2 kg/GJ | D1: CH4 g/GJ | E1: N2O g/GJ | F1: SO2 g/GJ | G1: NOx g/GJ | H1: PM2.5 g/GJ
A2: Centrale kraftværker og kraftvarmeværker
A3: Ledningsgas | B3: Dampturbine | C3: Se tabel 14 | D3: 1 | E3: 1 | F3: 0.4 | G3: 19.6 | H3: 0.1
A4: Kul | B4: Dampturbine | C4: 74.1 | D4: 0.7 | E4: 0.6 | F4: 6.7 | G4: 52 | H4: 5
A5: Fuelolie | B5: Dampturbine | C5: 0 | D5: 3 | E5: 4 | F5: 11 | G5: 80 | H5: 47
A6: Halm* | B6: Dampturbine | C6: 0 | D6: 105 | E6: 4 | F6: 11 | G6: 73.5 | H6: 290
A7: Træ* | B7: Dampturbine | C7: 0 | D7: 3.1 | E7: 0.8 | F7: 1.9 | G7: 33 | H7: 4.8
A8: Træpiller | B8: Dampturbine | C8: 0 | D8: 3.1 | E8: 0.8 | F8: 1.9 | G8: 33 | H8: 4.8
A9: Decentrale kraftvarmeværker
A10: Ledningsgas | B10: Gasturbine | C10: Se tabel 14 | D10: 1.7 | E10: 1 | F10: 0.4 | G10: 48 | H10: 0.05
A11: Ledningsgas | B11: Motor | C11: Se tabel 14 | D11: 481 | E11: 0.6 | F11: 0.5 | G11: 135 | H11: 0.16
A12: Halm* | B12: Dampturbine | C12: 0 | D12: 0.5 | E12: 1.1 | F12: 49 | G12: 125 | H12: 1.11
A13: Træ* | B13: Dampturbine | C13: 0 | D13: 3.1 | E13: 0.8 | F13: 1.9 | G13: 81 | H13: 4.82
A14: Træpiller | B14: Dampturbine | C14: 0 | D14: 3.1 | E14: 0.8 | F14: 1.9 | G14: 81 | H14: 4.82
A15: Affald | B15: Dampturbine | C15: 42.5 | D15: 0.3 | E15: 1.2 | F15: 8.3 | G15: 79 | H15: 0.29
A16: Biogas*** | B16: Motor | C16: 0 | D16: 434 | E16: 1.6 | F16: 19.2 | G16: 202 | H16: 0.21
A17: Ren varmeproduktion på decentrale værker og lingende
A18: Ledningsgas | B18: Se tabel 14 | C18: Se tabel 14 | D18: 1 | E18: 1 | F18: 0.4 | G18: 31.7 | H18: 0.1
A19: Halm | B19: Se tabel 14 | C19: 0 | D19: 30 | E19: 4 | F19: 115 | G19: 90 | H19: 12
A20: Træ | B20: Se tabel 14 | C20: 0 | D20: 11 | E20: 4 | F20: 11 | G20: 90 | H20: 10
A21: Træpiller | B21: Se tabel 14 | C21: 0 | D21: 3 | E21: 4 | F21: 11 | G21: 90 | H21: 10
A22: Biogas*** | B22: Se tabel 14 | C22: 0 | D22: 1 | E22: 0.1 | F22: 25 | G22: 28 | H22: 1.5
A23: Husholdninger
A24: Ledningsgas | B24: Se tabel 14 | C24: Se tabel 14 | D24: 1 | E24: 1 | F24: 0.4 | G24: 19.6 | H24: 0.1
A25: Gasolie | B25: Se tabel 14 | C25: 74.1 | D25: 0.7 | E25: 0.6 | F25: 6.7 | G25: 52 | H25: 5
A26: Træpiller | B26: Se tabel 14 | C26: 0 | D26: 3 | E26: 4 | F26: 11 | G26: 80 | H26: 47
A27: Brænde og andre træprodukter | B27: Se tabel 14 | C27: 0 | D27: 105 | E27: 4 | F27: 11 | G27: 73.5 | H27: 290
A28: Industri og lidnende
A29: Ledningsgas | B29: Industrielle kedler | C29: Se tabel 14 | D29: 1 | E29: 1 | F29: 0.001 | G29: 0.0317 | H29: 0.1
A30: Raffinaderigas | B30: Raffinaderier | C30: 56.5 | D30: 1 | E30: 1 | F30: 0.001 | G30: 0.056 | H30: 5
A32: Emissionfactor in the electircity grid
B33: CO2 kg/MWh | D33: CH4/g/MWh | F33: N20 g/MWh | H33: SO2 g/MWh | J33: Nox g/MWh | L33: PM2,5 g/MWh
B34: Produktion | C34: forbrug* | D34: Produktion | E34: forbrug* | F34: Produktion | G34: forbrug* | H34: Produktion | I34: forbrug* | J34: Produktion | K34: forbrug* | L34: Produktion | M34: forbrug*
A35: 2022 | B35: 59 | C35: 62 | D35: 105 | E35: 111 | F35: 2.2 | G35: 2.3 | H35: 22 | I35: 23 | J35: 197 | K35: 210 | L35: 0.5 | M35: 0.6
A36: 2023 | B36: 46 | C36: 48 | D36: 87 | E36: 92 | F36: 2 | G36: 2.1 | H36: 16 | I36: 17 | J36: 187 | K36: 198 | L36: 0.5 | M36: 0.5
A37: 2024 | B37: 38 | C37: 41 | D37: 74 | E37: 78 | F37: 1.8 | G37: 1.9 | H37: 15 | I37: 16 | J37: 167 | K37: 177 | L37: 0.5 | M37: 0.5
A38: 2025 | B38: 35 | C38: 37 | D38: 66 | E38: 71 | F38: 1.6 | G38: 1.7 | H38: 14 | I38: 15 | J38: 151 | K38: 161 | L38: 0.4 | M38: 0.5
A39: 2026 | B39: 28 | C39: 29 | D39: 56 | E39: 59 | F39: 1.4 | G39: 1.4 | H39: 12 | I39: 13 | J39: 130 | K39: 138 | L39: 0.4 | M39: 0.4
A40: 2027 | B40: 23 | C40: 24 | D40: 50 | E40: 53 | F40: 1.2 | G40: 1.2 | H40: 10 | I40: 11 | J40: 113 | K40: 120 | L40: 0.4 | M40: 0.4
A41: 2028 | B41: 17 | C41: 18 | D41: 43 | E41: 45 | F41: 1 | G41: 1.1 | H41: 8 | I41: 8 | J41: 99 | K41: 105 | L41: 0.3 | M41: 0.4
A42: 2029 | B42: 8 | C42: 9 | D42: 38 | E42: 41 | F42: 0.9 | G42: 1 | H42: 4 | I42: 4 | J42: 90 | K42: 95 | L42: 0.3 | M42: 0.3
A43: 2030 | B43: 7 | C43: 7 | D43: 34 | E43: 37 | F43: 0.8 | G43: 0.8 | H43: 3 | I43: 3 | J43: 78 | K43: 83 | L43: 0.3 | M43: 0.3
A44: 2031 | B44: 7 | C44: 7 | D44: 34 | E44: 37 | F44: 0.8 | G44: 0.8 | H44: 3 | I44: 3 | J44: 78 | K44: 83 | L44: 0.3 | M44: 0.3
A45: 2032 | B45: 7 | C45: 7 | D45: 34 | E45: 37 | F45: 0.8 | G45: 0.8 | H45: 3 | I45: 3 | J45: 78 | K45: 83 | L45: 0.3 | M45: 0.3
A46: 2033 | B46: 7 | C46: 7 | D46: 34 | E46: 37 | F46: 0.8 | G46: 0.8 | H46: 3 | I46: 3 | J46: 78 | K46: 83 | L46: 0.3 | M46: 0.3
... A58: 2045 | B58: 7 | C58: 7 | D58: 34 | E58: 37 | F58: 0.8 | G58: 0.8 | H58: 3 | I58: 3 | J58: 78 | K58: 83 | L58: 0.3 | M58: 0.3
A59: * nattab svarende til 5,8 %
A72: CO2 - Table 14
A73: Brændsel | B73: Emissionsfaktor (eller foreløbig emissionsfaktor for biomasse) | C73: Enhed (Emissionsfaktor) | D73: Biomassefraktion for kulstofindhold (%) | E73: Noter
A74: Naturgas | B74: 55.47 | C74: ton CO2/TJ is the same as Kg/GJ | D74: - | E74: G) H) I)
A75: Bionaturgas | B75: 55.55 | C75: ton CO2/TJ | D75: - | E75: F) D) I)
A76: Butan | B76: 66.24 | C76: ton CO2/TJ | D76: - | E76: -
A77: Fuelolie | B77: 79.03 | C77: ton CO2/TJ | D77: - | E77: J)
A78: Spildolie | B78: 73.3 | C78: ton CO2/TJ | D78: - | E78: E)
A79: Gasolie/dieselolie | B79: 74.1 | C79: ton CO2/TJ | D79: - | E79: B)
A80: Benzin | B80: 73 | C80: ton CO2/TJ | D80: - | E80: B)
A81: Methanol | B81: 68.96 | C81: ton CO2/TJ | D81: - | E81: -
A82: LPG | B82: 64.8 | C82: ton CO2/TJ | D82: - | E82: B)
A83: Kul | B83: 94.2 | C83: ton CO2/TJ | D83: - | E83: J)
A84: Petrokoks | B84: 93 | C84: ton CO2/TJ | D84: - | E84: -
A85: Koks | B85: 107 | C85: ton CO2/TJ | D85: - | E85: - | F85: kg/TJ | G85: Kg/GJ | H85: Kg/MJ
A86: Affald | B86: 105.8 | C86: ton CO2/TJ | D86: 0.5983 | E86: F) M) | F86: =B86*1000 -> 105800 | G86: =F86/1000 -> 105.8 | H86: =G86/1000 -> 0.1058 | I86: =(1-D86)*H86 -> 0.04249986
A87: Biogas | B87: 84.1 | C87: ton CO2/TJ | D87: - | E87: F)
A88: Halm | B88: 100 | C88: ton CO2/TJ | D88: - | E88: A) E) F)
A89: Træpiller | B89: 112 | C89: ton CO2/TJ | D89: - | E89: A) E) F)
A90: Træaffald | B90: 112 | C90: ton CO2/TJ | D90: - | E90: A) E) F)
A91: Træflis | B91: 112 | C91: ton CO2/TJ | D91: - | E91: A) E) F)
A92: Anden fast biomasse | B92: 100 | C92: ton CO2/TJ | D92: - | E92: E) F)
A93: Rapsolie | B93: 70.8 | C93: ton CO2/TJ | D93: - | E93: B) C) F)
A94: Bioethanol | B94: 72 | C94: ton CO2/TJ | D94: - | E94: B) C) F)
A95: Biodiesel | B95: 70.8 | C95: ton CO2/TJ | D95: - | E95: B) C) E) F)
A96: Bioolie og anden flydende biobrændsel | B96: 79.6 | C96: ton CO2/TJ | D96: - | E96: B) C) F)

Sheet emission cost
A1: 2021 - Priser kr./kg | B1: Sektor | C1: SO2/SO4 | D1: NOx | E1: PM2.5 | J1: https://syddanskuni-my.sharepoint.com/personal/busterhansen_sdu_dk/Documents/Sector%20coupling/Literature/CO2-emission%20factor/soeb22.pdf
A2: SNAP1 | B2: Større forbrændingsanlæg, inkl. affaldsforbrændingsanlæg | C2: 13 | D2: 12 | E2: 60
A3: SNAP2 | B3: Forbrændingsanlæg i husholdninger mv. | C3: 33 | D3: 48 | E3: 290
A4: SNAP3 | B4: Industrielle forbrændingsanlæg | C4: 16 | D4: 15 | E4: 73
A6: CO2-kvotepris
A8: Kr./ton, 2023-priser | B8: 2023 | C8: 2024 | D8: 2025
A9: CO2-kvoter | B9: 636 | C9: 654 | D9: 678
A10: Kilde: Finansministeriet.
A12: Analyseforudsætninger 2022 (AF22) til sammenligning
A13: Kr./ton, 2023-priser | B13: 2023 | C13: 2024 | D13: 2025
A14: CO2-kvoter | B14: 678.72 | C14: 701.52 | D14: 726.63
A17: Emissionkost for Affald Kr/ton | B17: 195.7 | C17: https://www.pwc.dk/da/afgiftsvejledningen/godtgorelse-satser.html#bilag-6
A19: Afgift | B19: Enhed | C19: 2025
A20: CO2-kvoter | B20: kr/ton
A21: CO2-afgift affald | B21: kr/ton | C21: 440.1524
A22: CO2-afgift oliekedel | B22: kr/liter | C22: 0.93592844
A23: CO2-afgift gaskedel | B23: kr/m3 | C23: 0.98270538
A24: CO2-afgift gasmotor | B24: kr/m3 | C24: 0.98270538
A25: Affaldvarmeafgift netto | B25: kr/GJ | C25: 13.295184
A26: Tillægsafgift netto | B26: kr/GJ | C26: 26.5
A27: Tillægsafgiftsrabat RGK | B27: % | C27: 10
A28: Tillægsafgiftsrabat krit. | B28: % | C28: 7
A29: Energiafgift biooliekedel | B29: kr/liter | C29: 2.293
A30: Energiafgift oliekedel | B30: kr/liter | C30: 1.8390716
A31: Energiafgift gaskedel | B31: kr/m3 | C31: 1.9582946
A32: Energiafgift gasmotor | B32: kr/m3 | C32: 1.9582946
A33: NOx-afgift affald | B33: kr/kgNOx | C33: =5.3 -> 5.3
A34: NOx-afgift fliskedel | B34: kr/GJ | C34: 0.5
A35: NOx-afgift oliekedel | B35: kr/liter | C35: 0.1
A36: NOx-afgift gaskedel | B36: kr/m3 | C36: 0.009
A37: NOx-afgift gasmotor | B37: kr/m3 | C37: 0.3

Sheet Fuel cost
A1: Kul, råolie og naturgas
A2: Danske priser an forbrugssted (2023-priser, kr./GJ)
A3: An centralt værk | B3: 2024 | C3: 2025
A4: Kul | B4: 61.69 | C4: 41.68
A5: Fuelolie | B5: 95.84 | C5: 90.9
A6: Gasolie | B6: 169.13 | C6: 127.53
A7: Naturgas | B7: 238.24 | C7: 111.79
A9: An decentralt værk | B9: 2024 | C9: 2025
A10: Gasolie | B10: 174.63 | C10: 133.03
A11: Naturgas | B11: 243.44 | C11: 117.25
A12: Kilde: Energistyrelsens fremskrivninger. Tillæg til importpriserne for at nå frem til forbrugssted(raffinaderiomkostninger og omkostninger til transport m.m.) er uændrede ift. AF22, men dog opregnet til 2023-prisniveau.
A14: Træpiller, træflis og halm
A16: Danske priser an forbrugssted (2023-priser, kr./GJ)
A17: An centralt værk | B17: 2024 | C17: 2025
A18: Halm | B18: 62.11 | C18: 53.78
A19: Træflis | B19: 72.97 | C19: 63.24
A20: Træpiller | B20: 103.75 | C20: 84.43
A22: An decentralt værk | B22: 2024 | C22: 2025
A23: Halm | B23: 57.78 | C23: 50.03
A24: Træflis | B24: 67.91 | C24: 58.86
A25: Træpiller | B25: 109.04 | C25: 89.68
A26: Kilde: Energistyrelsens fremskrivninger. Tillæg til importpriserne for at nå frem til forbrugssted er uændrede ift. AF22, men dog opregnet til 2023-prisniveau.
A28: Analyseforudsætninger 2022 (AF22) til sammenligning
A30: Danske priser an forbrugssted (2023-priser, kr./GJ)
A31: An centralt værk | B31: 2024 | C31: 2025
A32: Kul | B32: 23.23 | C32: 23.2
A33: Fuelolie | B33: 73.13 | C33: 69.98
A34: Gasolie | B34: 111.28 | C34: 108.14
A35: Naturgas | B35: 51.76 | C35: 47.91
A36: Halm | B36: 50.48 | C36: 50.68
A37: Træflis | B37: 58.97 | C37: 59.21
A38: Træpiller | B38: 81.41 | C38: 80.88
A40: An decentralt værk | B40: 2024 | C40: 2025
A41: Gasolie | B41: 116.64 | C41: 113.5
A42: Naturgas | B42: 57.07 | C42: 53.34
A43: Halm | B43: 48.46 | C43: 48.66
... A45: Træpiller | B45: 86.66 | C45: 86.12
A48: affald kr / ton | B48: 2021
A49: Gns. takst for dedikerede anlæg (kr. pr. ton) | B49: 484
A50: Gns. takst for dedikerede og multifyrede anlæg (kr. pr. ton) | B50: 483
B52: This is the breakeven price in DK | C52: direct connection to a renewable energy source | D52: by water electrolysis, utilizing grid electricity, averaged | E52: 3.23 (breakeven point) | G52: Model value
A53: Hydrogen cost EUR/kg | B53: =G53 -> 5 | C53: 6.61 | D53: 7.94 | E53: 3.23 | F53: =AVERAGE(D53:E53) -> 5.585 | G53: 5
A54: statestik min | B54: 3.85
A55: statestik max | B55: =D53 -> 7.94
A56: TSO | B56: =(5.6+0.74)*10 -> 63.4 | C56: https://energinet.dk/el/elmarkedet/tariffer/aktuelle-tariffer/
A57: DSO | B57: 9.59 | C57: https://n1.dk/gaeldende-priser
A58: System tarif | B58: =B57+B56 -> 72.99

Sheet Annuitetsberegning
A15: https://syddanskuni-my.sharepoint.com/personal/busterhansen_sdu_dk/Documents/Sector%20coupling/Literature/Economics/tillaeg_annuitetsregning.pdf

Sheet Grid loss
A2: nettabet, | B2: 0.058

Sheet Electricity price 2024
A1: Area Name | B1: DK1 DKK/MWh 2024
A2: 45293 | B2: 228.03999
A3: 45293.042 | B3: 149.61999
A4: 45293.083 | B4: 231.32001
A5: 45293.125 | B5: 137.09
A6: 45293.167 | B6: 82.599998
A7: 45293.208 | B7: 102.73
A8: 45293.25 | B8: 355.07001
A9: 45293.292 | B9: 433.12
A10: 45293.333 | B10: 489.54999
A11: 45293.375 | B11: 482.54999
A12: 45293.417 | B12: 514.22998
A13: 45293.458 | B13: 548.21997
... A8761: 45657.958 | B8761: 3.88

Sheet Heat demand
A1: Time | B1: Esbjerg | C1: Varde | D1: Bramming | E1: Total
A2: 46388 | B2: 134.03 | C2: 22.55 | D2: 9.02 | E2: 165.6
A3: 46388.042 | B3: 139.48 | C3: 23 | D3: 9.2 | E3: 171.68
A4: 46388.083 | B4: 134.42 | C4: 22.75 | D4: 9.1 | E4: 166.27
A5: 46388.125 | B5: 134.24 | C5: 23.05 | D5: 9.22 | E5: 166.51
A6: 46388.167 | B6: 129.73 | C6: 28.5 | D6: 11.4 | E6: 169.63
A7: 46388.208 | B7: 129.4 | C7: 29.5 | D7: 11.8 | E7: 170.7
A8: 46388.25 | B8: 130.7 | C8: 31.2 | D8: 12.48 | E8: 174.38
A9: 46388.292 | B9: 129.97 | C9: 34.4 | D9: 13.76 | E9: 178.13
A10: 46388.333 | B10: 131.99 | C10: 35.35 | D10: 14.14 | E10: 181.48
A11: 46388.375 | B11: 135.91 | C11: 33.9 | D11: 13.56 | E11: 183.37
A12: 46388.417 | B12: 143.71 | C12: 32.5 | D12: 13 | E12: 189.21
A13: 46388.458 | B13: 152.95 | C13: 26.5 | D13: 10.6 | E13: 190.05
... A8761: 46752.958 | B8761: 147.7 | C8761: 25.29 | D8761: 10.12 | E8761: 183.11

Sheet Electricity demand
A1: 159.61639
A2: 151.86666
A3: 140.37633
A4: 126.68792
A5: 113.13912
A6: 103.06161
A7: 98.607543
A8: 101.00356
A9: 114.87128
A10: 143.69404
A11: 180.05186
A12: 212.76735
... A8760: 189.58416

Sheet PtX Cost and Renevue
D2: Max | E2: =MAX('Electricity price 2024'!#REF!) -> #REF! | F2: 926 | O2: Emissionfactor CO2 | P2: 41 | Q2: kg/ MWh | R2: =P2*$I$4 -> 4100 | T2: Excess DH | U2: H2 Kg
D3: Min | E3: =MIN('Electricity price 2024'!#REF!) -> #REF! | G3: Cooling cost | I3: Electricity | O3: Emissionfactor NOx | P3: 0.0019 | Q3: kg/ MWh | R3: =P3*$I$4 -> 0.19 | T3: 40 | U3: 1166
D4: Avg | E4: =AVERAGE('Electricity price 2024'!#REF!) -> #REF! | F4: Amount (MWh or Kg) | G4: 13.3 | H4: 330 | I4: 100 | O4: Emissionfactor SOx | P4: 0.177 | Q4: kg/ MWh | R4: =P4*$I$4 -> 17.7 | T4: =T3*Cockpit!AF17 -> 7200 | U4: =U3*((Cockpit!AF16)) -> 43491.8 | V4: =U3*(Cockpit!AF16) -> 43491.8
D5: Cost and revenue is the same | E5: 660.5 | F5: Cost | G5: =G4*Cockpit!AF18 -> 798 | H5: =H4*Cockpit!AF18 -> 19800 | I5: =I4*F2 -> 92600 | J5: 0 | K5: =E4*I4 -> #REF! | L5: =I4*E6 -> 65750 | M5: =E5*I4 -> 66050 | O5: Emission cost CO2 | P5: 0.70152 | Q5: kr/kg | R5: =R2*P5 -> 2876.232
E6: 657.5 | G6: Max | H6: min | I6: Max | J6: min | K6: avg | L6: =D5 -> Cost and revenue is the same | O6: Emission cost Nox | P6: 12 | Q6: kr./kg | R6: =R3*P6 -> 2.28
O7: Emission cost Sox | P7: 13 | Q7: kr./kg | R7: =R4*P7 -> 230.1
H8: Electricity | R8: =SUM(R5:R7) -> 3108.612
H9: Cost | I9: Revenue
F10: hour 1 | H10: =$G$5+I5+$R$8 -> 96506.612 | I10: =$T$4+$U$4 -> 50691.8 | J10: =I10-H10 -> -45814.812
F11: Min | H11: =$G$5+J5+$R$8 -> 3906.612 | I11: =$T$4+$U$4 -> 50691.8 | J11: =I11-H11 -> 46785.188
F12: Avg | H12: =$G$5+K5+$R$8 -> #REF! | I12: =$T$4+$U$4 -> 50691.8 | J12: =I12-H12 -> #REF!
H16: Cooling cost
H17: Cost | I17: Revenue
F18: Max | H18: =$G$5+$K$5+$R$8 -> #REF! | I18: =$T$4+$U$4 -> 50691.8 | J18: =I18-H18 -> #REF!
F19: Min | H19: =$H$5+$K$5+$R$8 -> #REF! | I19: =$T$4+$U$4 -> 50691.8 | J19: =I19-H19 -> #REF!
F25: All
H26: Cost | I26: Revenue
F27: Max | H27: =$G$5+I5+$R$8 -> 96506.612 | I27: =$T$4+$U$4 -> 50691.8 | J27: =I27-H27 -> -45814.812
F28: Min | H28: =$H$5+J5+$R$8 -> 22908.612 | I28: =$T$4+$U$4 -> 50691.8 | J28: =I28-H28 -> 27783.188
F29: Avg | H29: =$H$5+K5+$R$8 -> #REF! | I29: =$T$4+$U$4 -> 50691.8 | J29: =I29-H29 -> #REF!
F30: zero at max cooling | H30: =$G$5+L5+$R$8 -> 69656.612 | I30: =$T$4+$U$4 -> 50691.8 | J30: =I30-H30 -> -18964.812
F31: zero at min cooling | H31: =$H$5+M5+$R$8 -> 88958.612 | I31: =$T$4+$U$4 -> 50691.8 | J31: =I31-H31 -> -38266.812

Sheet GHI
A1: GHI KWh/m2
A2: 0
A3: 0
A4: 0
A5: 0
A6: 0
A7: 0
A8: 0
A9: 0
A10: 27
A11: 90
A12: 137
A13: 151
... A8761: 0

Sheet 1.1 AEC 1 GW 
A1: Technology | C1: Hydrogen production via alkaline electrolysis (AEC) for 1 GW plant
A2: year | C2: 2020 | D2: 2025 | E2: 2030 | F2: 2040 | G2: 2050 | H2: 2020 | I2: 2020 | J2: 2050 | K2: 2050 | L2: Note | M2: Ref. In doc | N2: Ref
A3: est | C3: ctrl | D3: ctrl | E3: ctrl | F3: ctrl | G3: ctrl | H3: Lower | I3: Upper | J3: Lower | K3: Upper
A4: cat | B4: par
A5: Energy/technical data
B6: Typical total plant size [MW input_e] | C6: 1000 | D6: 1000 | E6: 1000 | F6: 1000 | G6: 1000 | H6: 1000 | I6: 1000 | J6: 1000 | K6: 1000
B7: Typical total plant size [kgH2/day of max output] | C7: =(1/C10)*C6*1000*24 -> 458524.69 | D7: =(1/D10)*D6*1000*24 -> 466562.99 | E7: =(1/E10)*E6*1000*24 -> 493786 | F7: =(1/F10)*F6*1000*24 -> 518851.61 | G7: =(1/G10)*G6*1000*24 -> 555555.56 | H7: =(1/H10)*H6*1000*24 -> 481918.3 | I7: =(1/I10)*I6*1000*24 -> 437297.12 | J7: =(1/J10)*J6*1000*24 -> 568448.22 | K7: =(1/K10)*K6*1000*24 -> 543234.74 | L7: A, B
B8: Input
B9: Electricity (% total input [MWh/MWh]) | C9: 100 | D9: 100 | E9: 100 | F9: 100 | G9: 100 | H9: 100 | I9: 100 | J9: 100 | K9: 100
B10: Electricity consumption [stack level, kWh/kgH2] | C10: 52.341783 | D10: 51.44 | E10: 48.604052 | F10: 46.256 | G10: 43.2 | H10: 49.800973 | I10: 54.882594 | J10: 42.220204 | K10: 44.179796 | L10: C, D | M10: [4], [5], [6], [7] | N10: [1], [2], [3], [4]
B11: Electricity consumption [stack+BOP level, kWh/kgH2] | C11: 57.685145 | D11: 56.691302 | E11: 53.565843 | F11: 50.978088 | G11: 47.610114 | H11: 54.884953 | I11: 60.485336 | J11: 46.530294 | K11: 48.689933 | L11: E | M11: [4], [5], [6], [7] | N11: [1], [2], [3], [4]
B12: Ultrapure Water for electrolysis [kg/MWh input_e] | C12: =C19+(C19*8) -> 171.94676 | D12: =D19+(D19*8) -> 174.96112 | E12: =E19+(E19*8) -> 185.16975 | F12: =F19+(F19*8) -> 194.56935 | G12: =G19+(G19*8) -> 208.33333 | H12: =H19+(H19*8) -> 180.71936 | I12: =I19+(I19*8) -> 163.98642 | J12: =J19+(J19*8) -> 213.16808 | K12: =K19+(K19*8) -> 203.71303
B13: Output | P13: MWh | Q13: 1
B14: Hydrogen Output (% total input_e [MWh/MWh]) | C14: =(33.3/C11)*100 -> 57.727167 | D14: =(33.3/D11)*100 -> 58.739169 | E14: =(33.3/E11)*100 -> 62.166481 | F14: =(33.3/F11)*100 -> 65.322182 | G14: =(33.3/G11)*100 -> 69.943122 | H14: =(33.3/H11)*100 -> 60.672367 | I14: =(33.3/I11)*100 -> 55.054666 | J14: =(33.3/J11)*100 -> 71.566278 | K14: =(33.3/K11)*100 -> 68.391961 | L14: F | P14: Hydrogen Output (% total input_e [MWh e /MWh H2]) | Q14: 0.577
B15: ΔE from HHV to LHV (% total input_e [MWh/MWh]) | C15: =(C19*39.4/1000*100)-(33.3/C10)*100 -> 11.654169 | D15: =(D19*39.4/1000*100)-(33.3/D10)*100 -> 11.858476 | E15: =(E19*39.4/1000*100)-(33.3/E10)*100 -> 12.550394 | F15: =(F19*39.4/1000*100)-(33.3/F10)*100 -> 13.187478 | G15: =(G19*39.4/1000*100)-(33.3/G10)*100 -> 14.12037 | H15: =(H19*39.4/1000*100)-(33.3/H10)*100 -> 12.248757 | I15: =(I19*39.4/1000*100)-(33.3/I10)*100 -> 11.114635 | J15: =(J19*39.4/1000*100)-(33.3/J10)*100 -> 14.448059 | K15: =(K19*39.4/1000*100)-(33.3/K10)*100 -> 13.807216 | L15: G, H | P15: output MWh H2 | Q15: =Q14*Q13 -> 0.577 | R15: =Q15/Q17 -> 0.030201209 | S15: =Q17/Q15 -> 33.111257
B16: Heat loss (% total input_e [MWh/MWh]) | C16: =100-C14-C15 -> 30.618663 | D16: =100-D14-D15 -> 29.402355 | E16: =100-E14-E15 -> 25.283124 | F16: =100-F14-F15 -> 21.490339 | G16: =100-G14-G15 -> 15.936508 | H16: =100-H14-H15 -> 27.078877 | I16: =100-I14-I15 -> 33.830699 | J16: =100-J14-J15 -> 13.985663 | K16: =100-K14-K15 -> 17.800823 | P16: MWh | Q16: 1
B17: - hereof unrecoverable heat loss [%-points of heat loss] | C17: 3 | D17: 3 | E17: 3 | F17: 3 | G17: 3 | H17: 3 | I17: 3 | J17: 3 | K17: 3 | L17: I | P17: Hydrogen [kg/MWh e] | Q17: 19.105195 | R17: =Q18/Q14 -> 33.111257 | S17: =Q14/Q18 -> 0.030201209
B18: - hereof recoverable for district heating [%-points of heat loss] | C18: =C16-C17 -> 27.618663 | D18: =D16-D17 -> 26.402355 | E18: =E16-E17 -> 22.283124 | F18: =F16-F17 -> 18.490339 | G18: =G16-G17 -> 12.936508 | H18: =H16-H17 -> 24.078877 | I18: =I16-I17 -> 30.830699 | J18: =J16-J17 -> 10.985663 | K18: =K16-K17 -> 14.800823 | L18: J | P18: output KG | Q18: =Q17*Q16 -> 19.105195
B19: Hydrogen [kg/MWh input_e] | C19: =(C7/24)/C6 -> 19.105195 | D19: =(D7/24)/D6 -> 19.440124 | E19: =(E7/24)/E6 -> 20.574416 | F19: =(F7/24)/F6 -> 21.618817 | G19: =(G7/24)/G6 -> 23.148148 | H19: =(H7/24)/H6 -> 20.079929 | I19: =(I7/24)/I6 -> 18.220713 | J19: =(J7/24)/J6 -> 23.685343 | K19: =(K7/24)/K6 -> 22.634781
B20: Forced outage [%] | C20: 3 | D20: 3 | E20: 3 | F20: 3 | G20: 3 | H20: 3 | I20: 3 | J20: 3 | K20: 3 | L20: K
B21: Planned outage [days per year] | C21: 11 | D21: 11 | E21: 11 | F21: 11 | G21: 11 | H21: 11 | I21: 11 | J21: 11 | K21: 11 | L21: K
B22: Technical lifetime [years] | C22: 25 | D22: 25 | E22: 25 | F22: 25 | G22: 25 | H22: 20 | I22: 30 | J22: 20 | K22: 30 | L22: K | R22: =Q14*Q17 -> 11.023698
B23: Frequency of stack replacement [h] | C23: 70000 | D23: 80000 | E23: 92500 | F23: 94500 | G23: 101500 | H23: 61500 | I23: 78500 | J23: 83000 | K23: 120000 | L23: C, D, L | M23: [4], [5], [6], [7], [37] | N23: [1], [2], [3], [4], [5]
B24: Construction time [years] | C24: 3 | D24: 3 | E24: 3 | F24: 3 | G24: 3 | H24: 3 | I24: >3,0 | J24: 3 | K24: >3,0 | L24: M
A25: Financial data
B26: Specific investment [€/kW of total input_e] | C26: 1100 | D26: 800 | E26: 500 | F26: 400 | G26: 275 | H26: 875 | I26: 1325 | J26: 225 | K26: 325 | L26: D, N, O | M26: [5], [37], [35], [36], [40], [41], [42] | N26: [2], [4], [5], [6], [7], [8], [9], [10]
B27: - hereof electrolyser stack [€/kW of total input_e] | C27: =C$26*23.8237503698052% -> 262.06125 | D27: =D$26*23.8237503698052% -> 190.59 | E27: =E$26*23.8237503698052% -> 119.11875 | F27: =F$26*23.8237503698052% -> 95.295001 | G27: =G$26*23.8237503698052% -> 65.515314 | H27: =H$26*23.8237503698052% -> 208.45782 | I27: =I$26*23.8237503698052% -> 315.66469 | J27: =J$26*23.8237503698052% -> 53.603438 | K27: =K$26*23.8237503698052% -> 77.427189 | L27: P, Q
B28: - hereof electrolyser system [€/kW of total input_e] | C28: =C$26*51.1531229792167% -> 562.68435 | D28: =D$26*51.1531229792167% -> 409.22498 | E28: =E$26*51.1531229792167% -> 255.76561 | F28: =F$26*51.1531229792167% -> 204.61249 | G28: =G$26*51.1531229792167% -> 140.67109 | H28: =H$26*51.1531229792167% -> 447.58983 | I28: =I$26*51.1531229792167% -> 677.77888 | J28: =J$26*51.1531229792167% -> 115.09453 | K28: =K$26*51.1531229792167% -> 166.24765 | L28: P, Q
B29: - hereof BOP [€/kW of total input_e] | C29: =C$26*12.820203949911% -> 141.02224 | D29: =D$26*12.820203949911% -> 102.56163 | E29: =E$26*12.820203949911% -> 64.10102 | F29: =F$26*12.820203949911% -> 51.280816 | G29: =G$26*12.820203949911% -> 35.255561 | H29: =H$26*12.820203949911% -> 112.17678 | I29: =I$26*12.820203949911% -> 169.8677 | J29: =J$26*12.820203949911% -> 28.845459 | K29: =K$26*12.820203949911% -> 41.665663 | L29: P, Q
B30: - hereof Control System [€/kW of total input_e] | C30: =C$26*4.96790209244097% -> 54.646923 | D30: =D$26*4.96790209244097% -> 39.743217 | E30: =E$26*4.96790209244097% -> 24.83951 | F30: =F$26*4.96790209244097% -> 19.871608 | G30: =G$26*4.96790209244097% -> 13.661731 | H30: =H$26*4.96790209244097% -> 43.469143 | I30: =I$26*4.96790209244097% -> 65.824703 | J30: =J$26*4.96790209244097% -> 11.17778 | K30: =K$26*4.96790209244097% -> 16.145682 | L30: P, Q
B31: - hereof Civil Infrastructure [€/kW of total input_e] | C31: =C$26*2.92880051293232% -> 32.216806 | D31: =D$26*2.92880051293232% -> 23.430404 | E31: =E$26*2.92880051293232% -> 14.644003 | F31: =F$26*2.92880051293232% -> 11.715202 | G31: =G$26*2.92880051293232% -> 8.0542014 | H31: =H$26*2.92880051293232% -> 25.627004 | I31: =I$26*2.92880051293232% -> 38.806607 | J31: =J$26*2.92880051293232% -> 6.5898012 | K31: =K$26*2.92880051293232% -> 9.5186017 | L31: P, Q
B32: - hereof Indirects [€/kW of total input_e] | C32: =C$26*4.30622009569378% -> 47.368421 | D32: =D$26*4.30622009569378% -> 34.449761 | E32: =E$26*4.30622009569378% -> 21.5311 | F32: =F$26*4.30622009569378% -> 17.22488 | G32: =G$26*4.30622009569378% -> 11.842105 | H32: =H$26*4.30622009569378% -> 37.679426 | I32: =I$26*4.30622009569378% -> 57.057416 | J32: =J$26*4.30622009569378% -> 9.6889952 | K32: =K$26*4.30622009569378% -> 13.995215 | L32: P, Q
B33: Specific investment [€/kgH2/day of max output] | C33: =C26/(C7/1000/C6) -> 2398.9984 | D33: =D26/(D7/1000/D6) -> 1714.6667 | E33: =E26/(E7/1000/E6) -> 1012.5844 | F33: =F26/(F7/1000/F6) -> 770.93333 | G33: =G26/(G7/1000/G6) -> 495 | H33: =H26/(H7/1000/H6) -> 1815.6605 | I33: =I26/(I7/1000/I6) -> 3029.9765 | J33: =J26/(J7/1000/J6) -> 395.81441 | K33: =K26/(K7/1000/K6) -> 598.26807 | L33: A, B, P
B34: - hereof equipment [%] | C34: 90 | D34: 90 | E34: 90 | F34: 90 | G34: 90 | H34: 90 | I34: 90 | J34: 90 | K34: 90 | L34: K, R
B35: - hereof installation [%] | C35: 10 | D35: 10 | E35: 10 | F35: 10 | G35: 10 | H35: 10 | I35: 10 | J35: 10 | K35: 10 | L35: K, R
B36: Fixed O&M [% of specific investment/year] | C36: 4 | D36: 4 | E36: 4 | F36: 4 | G36: 4 | H36: 4 | I36: 4 | J36: 4 | K36: 4 | L36: K, S | M36: [40] | N36: [8]
B37: Variable O&M [€/kWh of total input] | C37: - | D37: - | E37: - | F37: - | G37: - | L37: T
A38: Technology-specific data
B39: Current Density [A/cm2] | C39: 0.6 | D39: 0.8 | E39: 1 | F39: 1.2 | G39: 1.5 | H39: 0.4 | I39: 0.6 | J39: 1.2 | K39: 1.5 | L39: K, U | M39: [40] | N39: [8]
B40: Flexibility | C40: 0 | D40: 0 | E40: 0 | F40: 0 | G40: 0 | H40: 0 | I40: 0 | J40: 0 | K40: 0
B41: - cold start up time [min from 0 to 100%] | C41: 80 | D41: 60.416667 | E41: 30 | F41: <30 | G41: <30 | H41: 49.896036 | I41: 105 | J41: <30 | K41: <30 | L41: V | M41: [6], [40], [43] | N41: [3], [8], [11]
B42: Stack size [MW] | C42: 2 | D42: 5 | E42: 5 | F42: 10 | G42: 10 | H42: 1.5 | I42: 2.5 | J42: 10 | K42: 10 | M42: [6], [42], [44] | N42: [3], [10], [12]
B43: Degradation rate [%/1000h] | C43: 0.145 | D43: 0.13 | E43: 0.115 | F43: 0.11 | G43: 0.1 | H43: 0.12458759 | I43: 0.16541241 | J43: 0.11064996 | K43: 0.089350045 | L43: K, U, W | M43: [37], [40] | N43: [5], [8]
B44: Electrolyser Unit [m2/MW] | C44: 25 | D44: 21.276596 | E44: 12.5 | F44: 10.37234 | G44: 8.2978723 | H44: 37.5 | I44: 18.75 | J44: 12.446809 | K44: 6.2234043 | L44: X
B45: Plant Footprint [m2/MW input_e] | C45: 198 | D45: 168.51064 | E45: 99 | F45: 82.148936 | G45: 65.719149 | H45: 158.4 | I45: 297 | J45: 52.575319 | K45: 98.578723 | L45: X, Y
B46: Weight of Electrolyser Stack [MW/tons] | C46: 24 | D46: 18 | E46: 14.4 | F46: 12 | G46: 9.6 | H46: 16 | I46: 24 | J46: 7.68 | K46: 9.6 | L46: K, Z
C47: min | E47: Conversion factor
C48: =C41 -> 80 | D48: 1 | E48: =D48/C48 -> 0.0125
C49: 60 | D49: =E48*C49 -> 0.75 | F49: meaning that in 60 min the PtX can reach 75% of capacity (assumin linear ramping)
A51: Notes:
B52: A. For the unit regarding "day" a 100% load factor is assumed here (Where the system is operated at nominal capacity all 24 hours of the day). In operation the daily full load hours may vary and should therefore be adjusted for.
B53: B. Maximum hydrogen output per day, assuming 24 hours of full load operation in a day.
B54: C. The values were derived from multiple sources. 2025 and 2040 were calculated using linear regression based on the data provided in the mentioned references, encompassing the years 2020, 2030, and 2050.
B55: D. Upper and lower values are based on the average of the standard deviations found in the relevant data as shown in note C. Standard deviations for specific investments follow expected values from typical pre-FEED projects (20%).
B56: E. Based on reference [3], the energy consumption of the entire system (including both stack and balance of plant components) is estimated.
B57: F. Efficiency for AEC and PEMEC is calculated based on the electricity consumption of the stack and BOP level, and assuming the LHV of hydrogen. In the case of SOEC, energy supply for steam production is also included.
B58: G. The HHV electrolyser efficiency can be calculated as the sum of the rows: "ΔE from HHV to LHV" and "Hydrogen".
B59: H. The calculation is based on the HHV and LHV of hydrogen.
B60: I. 3% of the energy is estimated to be unrecoverable for AEC and PEMEC hydrogen plants.
B61: J. 50 °C (expected to increase to 70°C, by 2024).
B62: K. Based on internal projects and references performed at Ramboll including FEED projects and estimations from clients and from suppliers.
B63: L. Values have been rounded to nearest 500.
... B77: Z. Weight of stack is assuming wet conditions, where the contrarily to dry conditions, the weight of the electrolyte contributes to the total stack weight.
A80: References:
A81: [4] | B81: [1]. DNV, “Hydrogen Forecast to 2050”, 2022.
A82: [5] | B82: [2]. Monitor Deloitte, “Fueling the Future of Mobility: Hydrogen Electrolysers”, 2021.
A83: [6] | B83: [3]. IRENA, Making the breakthrough: Green hydrogen policies and technology costs, Abu Dhabi, 2021.
A84: [7] | B84: [4]. IEA, “The Future of Hydrogen, Seizing today's opportunities, Executive summary, and recommendations, Report prepared by the IEA for the G20, Japan,” IEA, 2019.
A85: [37] | B85: [5]. DoE Hydrogen and Fuel Cell Technologies Office, “Technical Targets for Liquid Alkaline Electrolysis,” DoE, [Accessed July 2023].
A86: [35] | B86: [6]. IRENA, “Green Hydrogen Cost Reduction: Scaling up electrolysers to meet the 1.5°C climate goal,” International Renewable Energy Agency, Abu Dhabi, 2020.
A87: [36] | B87: [7]. IEA, “Global Hydrogen Review 2023,” 2023.
A88: [40] | B88: [8]. Clean Hydrogen Partnership, Strategic Research and Innovation Agenda 2021-2027, 2022.
A89: [41] | B89: [9]. ISPT, “Gigawatt green hydrogen plant; State-of-the-art design and total installed capital costs,” 2020.
A90: [42] | B90: [10]. Fraunhofer Institute for Solar Energy Systems, “COST FORECAST FOR LOW-TEMPERATURE ELECTROLYSIS,” 2021.
A91: [43] | B91: [11]. Janke et.al., “Optimizing power-to-H2 participation in the Nord Pool electricity market: Effects of different bidding strategies on plant operation,” Renewable Energy, vol. 156, pp. 820-836, August 2020.
A92: [44] | B92: [12]. Böhm et.al., “Projecting cost development for future large-scale power-to-gas implementations by scaling effects,” Applied Energy, vol. 264, 15 April 2020.

Sheet 1.1 PEMEC 1 GW
A1: Technology | C1: Hydrogen production via PEMEC electrolysis for 1 GW plant
A2: year | C2: 2020 | D2: 2025 | E2: 2030 | F2: 2040 | G2: 2050 | H2: 2020 | I2: 2020 | J2: 2050 | K2: 2050 | L2: Note | M2: Ref. In doc | N2: Ref
A3: est | C3: ctrl | D3: ctrl | E3: ctrl | F3: ctrl | G3: ctrl | H3: Lower | I3: Upper | J3: Lower | K3: Upper
A4: cat | B4: par
A5: Energy/technical data
B6: Typical total plant size [MW input_e] | C6: 1000 | D6: 1000 | E6: 1000 | F6: 1000 | G6: 1000 | H6: 1000 | I6: 1000 | J6: 1000 | K6: 1000
B7: Typical total plant size [kgH2/day of max output] | C7: =(1/C10)*C6*1000*24 -> 426063.87 | D7: =(1/D10)*D6*1000*24 -> 445661.76 | E7: =(1/E10)*E6*1000*24 -> 473975.92 | F7: =(1/F10)*F6*1000*24 -> 499085.01 | G7: =(1/G10)*G6*1000*24 -> 537911.3 | H7: =(1/H10)*H6*1000*24 -> 439896.95 | I7: =(1/I10)*I6*1000*24 -> 413074.26 | J7: =(1/J10)*J6*1000*24 -> 571428.57 | K7: =(1/K10)*K6*1000*24 -> 508108.11 | L7: A, B
B8: Input
B9: Electricity (% total input [MWh/MWh]) | C9: 100 | D9: 100 | E9: 100 | F9: 100 | G9: 100 | H9: 100 | I9: 100 | J9: 100 | K9: 100
B10: Electricity consumption [stack level, kWh/kgH2] | C10: 56.329583 | D10: 53.8525 | E10: 50.635483 | F10: 48.088 | G10: 44.617021 | H10: 54.558233 | I10: 58.100933 | J10: 42 | K10: 47.234043 | L10: C, D | M10: [4], [5], [6], [7] | N10: [1], [2], [3], [4]
B11: Electricity consumption [stack+BOP level, kWh/kgH2] | C11: 63.326273 | D11: 60.541512 | E11: 56.92491 | F11: 54.061004 | G11: 50.158895 | H11: 61.334903 | I11: 65.317642 | J11: 47.216814 | K11: 53.100976 | L11: E | M11: [4], [5], [6], [7] | N11: [1], [2], [3], [4]
B12: Ultrapure Water for electrolysis [kg/MWh input_e] | C12: =C19+(C19*8) -> 159.77395 | D12: =D19+(D19*8) -> 167.12316 | E12: =E19+(E19*8) -> 177.74097 | F12: =F19+(F19*8) -> 187.15688 | G12: =G19+(G19*8) -> 201.71674 | H12: =H19+(H19*8) -> 164.96135 | I12: =I19+(I19*8) -> 154.90285 | J12: =J19+(J19*8) -> 214.28571 | K12: =K19+(K19*8) -> 190.54054
B13: Output
B14: Hydrogen Output (% total input_e [MWh/MWh]) | C14: =(33.3/C11)*100 -> 52.58481 | D14: =(33.3/D11)*100 -> 55.003582 | E14: =(33.3/E11)*100 -> 58.498116 | F14: =(33.3/F11)*100 -> 61.59708 | G14: =(33.3/G11)*100 -> 66.389022 | H14: =(33.3/H11)*100 -> 54.292088 | I14: =(33.3/I11)*100 -> 50.981632 | J14: =(33.3/J11)*100 -> 70.525724 | K14: =(33.3/K11)*100 -> 62.710711 | L14: F
B15: ΔE from HHV to LHV (% total input_e [MWh/MWh]) | C15: =(C19*39.4/1000*100)-(33.3/C10)*100 -> 10.829123 | D15: =(D19*39.4/1000*100)-(33.3/D10)*100 -> 11.327236 | E15: =(E19*39.4/1000*100)-(33.3/E10)*100 -> 12.046888 | F15: =(F19*39.4/1000*100)-(33.3/F10)*100 -> 12.685077 | G15: =(G19*39.4/1000*100)-(33.3/G10)*100 -> 13.671912 | H15: =(H19*39.4/1000*100)-(33.3/H10)*100 -> 11.180714 | I15: =(I19*39.4/1000*100)-(33.3/I10)*100 -> 10.498971 | J15: =(J19*39.4/1000*100)-(33.3/J10)*100 -> 14.52381 | K15: =(K19*39.4/1000*100)-(33.3/K10)*100 -> 12.914414 | L15: G, H
B16: Heat loss (% total input_e [MWh/MWh]) | C16: =100-C14-C15 -> 36.586067 | D16: =100-D14-D15 -> 33.669181 | E16: =100-E14-E15 -> 29.454996 | F16: =100-F14-F15 -> 25.717842 | G16: =100-G14-G15 -> 19.939066 | H16: =100-H14-H15 -> 34.527198 | I16: =100-I14-I15 -> 38.519397 | J16: =100-J14-J15 -> 14.950467 | K16: =100-K14-K15 -> 24.374874
B17: - hereof unrecoverable heat loss [%-points of heat loss] | C17: 3 | D17: 3 | E17: 3 | F17: 3 | G17: 3 | H17: 3 | I17: 3 | J17: 3 | K17: 3 | L17: I
B18: - hereof recoverable for district heating [%-points of heat loss] | C18: =C16-C17 -> 33.586067 | D18: =D16-D17 -> 30.669181 | E18: =E16-E17 -> 26.454996 | F18: =F16-F17 -> 22.717842 | G18: =G16-G17 -> 16.939066 | H18: =H16-H17 -> 31.527198 | I18: =I16-I17 -> 35.519397 | J18: =J16-J17 -> 11.950467 | K18: =K16-K17 -> 21.374874 | L18: J
B19: Hydrogen [kg/MWh input_e] | C19: =(C7/24)/C6 -> 17.752661 | D19: =(D7/24)/D6 -> 18.56924 | E19: =(E7/24)/E6 -> 19.748997 | F19: =(F7/24)/F6 -> 20.795209 | G19: =(G7/24)/G6 -> 22.412971 | H19: =(H7/24)/H6 -> 18.329039 | I19: =(I7/24)/I6 -> 17.211427 | J19: =(J7/24)/J6 -> 23.809524 | K19: =(K7/24)/K6 -> 21.171171
B20: Forced outage [%] | C20: 3 | D20: 3 | E20: 3 | F20: 3 | G20: 3 | H20: 3 | I20: 3 | J20: 3 | K20: 3 | L20: K
B21: Planned outage [days per year] | C21: 11 | D21: 11 | E21: 11 | F21: 11 | G21: 11 | H21: 11 | I21: 11 | J21: 11 | K21: 11 | L21: K
B22: Technical lifetime [years] | C22: 25 | D22: 25 | E22: 25 | F22: 25 | G22: 25 | H22: 20 | I22: 30 | J22: 20 | K22: 30 | L22: K
B23: Frequency of stack replacement [h] | C23: 55000 | D23: 65500 | E23: 77500 | F23: 90000 | G23: 105000 | H23: 46000 | I23: 64000 | J23: 86500 | K23: 123500 | L23: C, D, L | M23: [4], [5], [6], [7], [38] | N23: [1], [2], [3], [4], [5]
B24: Construction time [years] | C24: 3 | D24: 3 | E24: 3 | F24: 3 | G24: 3 | H24: 3 | I24: >3,0 | J24: 3 | K24: >3,0 | L24: M
A25: Financial data
B26: Specific investment [€/kW of total input_e] | C26: 1200 | D26: 900 | E26: 600 | F26: 450 | G26: 325 | H26: 950 | I26: 1450 | J26: 250 | K26: 400 | L26: D, N, O | M26: [5], [38], [35], [36], [40], [41], [42] | N26: [2], [4], [5], [6], [7], [8], [9], [10]
B27: - hereof electrolyser stack [€/kW of total input_e] | C27: =C$26*37.2414288657699% -> 446.89715 | D27: =D$26*37.2414288657699% -> 335.17286 | E27: =E$26*37.2414288657699% -> 223.44857 | F27: =F$26*37.2414288657699% -> 167.58643 | G27: =G$26*37.2414288657699% -> 121.03464 | H27: =H$26*37.2414288657699% -> 353.79357 | I27: =I$26*37.2414288657699% -> 540.00072 | J27: =J$26*37.2414288657699% -> 93.103572 | K27: =K$26*37.2414288657699% -> 148.96572 | L27: P, Q
B28: - hereof electrolyser system [€/kW of total input_e] | C28: =C$26*44.5425476918252% -> 534.51057 | D28: =D$26*44.5425476918252% -> 400.88293 | E28: =E$26*44.5425476918252% -> 267.25529 | F28: =F$26*44.5425476918252% -> 200.44146 | G28: =G$26*44.5425476918252% -> 144.76328 | H28: =H$26*44.5425476918252% -> 423.1542 | I28: =I$26*44.5425476918252% -> 645.86694 | J28: =J$26*44.5425476918252% -> 111.35637 | K28: =K$26*44.5425476918252% -> 178.17019 | L28: P, Q
B29: - hereof BOP [€/kW of total input_e] | C29: =C$26*6.61452551106052% -> 79.374306 | D29: =D$26*6.61452551106052% -> 59.53073 | E29: =E$26*6.61452551106052% -> 39.687153 | F29: =F$26*6.61452551106052% -> 29.765365 | G29: =G$26*6.61452551106052% -> 21.497208 | H29: =H$26*6.61452551106052% -> 62.837992 | I29: =I$26*6.61452551106052% -> 95.91062 | J29: =J$26*6.61452551106052% -> 16.536314 | K29: =K$26*6.61452551106052% -> 26.458102 | L29: P, Q
B30: - hereof Control System [€/kW of total input_e] | C30: =C$26*4.21993790889825% -> 50.639255 | D30: =D$26*4.21993790889825% -> 37.979441 | E30: =E$26*4.21993790889825% -> 25.319627 | F30: =F$26*4.21993790889825% -> 18.989721 | G30: =G$26*4.21993790889825% -> 13.714798 | H30: =H$26*4.21993790889825% -> 40.08941 | I30: =I$26*4.21993790889825% -> 61.1891 | J30: =J$26*4.21993790889825% -> 10.549845 | K30: =K$26*4.21993790889825% -> 16.879752 | L30: P, Q
B31: - hereof Civil Infrastructure [€/kW of total input_e] | C31: =C$26*3.0753399267524% -> 36.904079 | D31: =D$26*3.0753399267524% -> 27.678059 | E31: =E$26*3.0753399267524% -> 18.45204 | F31: =F$26*3.0753399267524% -> 13.83903 | G31: =G$26*3.0753399267524% -> 9.9948548 | H31: =H$26*3.0753399267524% -> 29.215729 | I31: =I$26*3.0753399267524% -> 44.592429 | J31: =J$26*3.0753399267524% -> 7.6883498 | K31: =K$26*3.0753399267524% -> 12.30136 | L31: P, Q
B32: - hereof Indirects [€/kW of total input_e] | C32: =C$26*4.30622009569378% -> 51.674641 | D32: =D$26*4.30622009569378% -> 38.755981 | E32: =E$26*4.30622009569378% -> 25.837321 | F32: =F$26*4.30622009569378% -> 19.37799 | G32: =G$26*4.30622009569378% -> 13.995215 | H32: =H$26*4.30622009569378% -> 40.909091 | I32: =I$26*4.30622009569378% -> 62.440191 | J32: =J$26*4.30622009569378% -> 10.76555 | K32: =K$26*4.30622009569378% -> 17.22488 | L32: P, Q
B33: Specific investment [€/kgH2/day of max output] | C33: =C26/(C7/1000/C6) -> 2816.4792 | D33: =D26/(D7/1000/D6) -> 2019.4687 | E33: =E26/(E7/1000/E6) -> 1265.8871 | F33: =F26/(F7/1000/F6) -> 901.65 | G33: =G26/(G7/1000/G6) -> 604.18883 | H33: =H26/(H7/1000/H6) -> 2159.5967 | I33: =I26/(I7/1000/I6) -> 3510.2647 | J33: =J26/(J7/1000/J6) -> 437.5 | K33: =K26/(K7/1000/K6) -> 787.23404 | L33: A, B, P
B34: - hereof equipment [%] | C34: 90 | D34: 90 | E34: 90 | F34: 90 | G34: 90 | H34: 90 | I34: 90 | J34: 90 | K34: 90 | L34: K, R
B35: - hereof installation [%] | C35: 10 | D35: 10 | E35: 10 | F35: 10 | G35: 10 | H35: 10 | I35: 10 | J35: 10 | K35: 10 | L35: K, R
B36: Fixed O&M [% of specific investment/year] | C36: 2 | D36: 2 | E36: 2 | F36: 2 | G36: 2 | H36: 2 | I36: 2 | J36: 2 | K36: 2 | L36: K, S | M36: [40] | N36: [8]
B37: Variable O&M [€/kWh of total input] | C37: - | D37: - | E37: - | F37: - | G37: - | L37: T
A38: Technology-specific data
B39: Current Density [A/cm2] | C39: 2.2 | D39: 2.8 | E39: 5 | F39: 7.5 | G39: 10 | H39: 1.5 | I39: 3 | J39: 7.5 | K39: 12.5 | L39: K, U | M39: [40] | N39: [8]
B40: Flexibility
B41: - cold start up time [min from 0 to 100%] | C41: 0.5 | D41: 0.3 | E41: 0.2 | F41: 0.16666667 | G41: 0.2 | H41: 0.3 | I41: 1 | J41: 0.1 | K41: 0.3 | L41: V | M41: [6], [40], [43] | N41: [3], [8], [11]
B42: Stack size [MW] | C42: 1.2 | D42: 1.5 | E42: 2 | F42: 5 | G42: 10 | H42: 1 | I42: 1.3 | J42: 10 | K42: 10 | L42: K | M42: [6], [42], [44] | N42: [3], [10], [12]
B43: Degradation rate [%/1000 h] | C43: 0.22 | D43: 0.1725 | E43: 0.125 | F43: 0.1 | G43: 0.1 | H43: 0.19 | I43: 0.25 | J43: 0.105 | K43: 0.095 | L43: K, U, W | M43: [38], [40] | N43: [5], [8]
B44: Electrolyser Unit [m2/MW] | C44: 10 | D44: 8.5106383 | E44: 5 | F44: 4.1489362 | G44: 3.1117021 | H44: 15 | I44: 7.5 | J44: 4.6675532 | K44: 2.3337766 | L44: X
B45: Plant Footprint [m2/MW input_e] | C45: 82 | D45: 69.787234 | E45: 41 | F45: 34.021277 | G45: 25.515957 | H45: 65.6 | I45: 123 | J45: 20.412766 | K45: 38.273936 | L45: X, Y
B46: Weight of Electrolyser Stack [MW/tons] | C46: 18 | D46: 14.142857 | E46: 7.92 | F46: 5.28 | G46: 3.96 | H46: 12.272727 | I46: 24.545455 | J46: 2.97 | K46: 4.95 | L46: K, Z
C47: min | E47: Conversion factor
C48: =C41*100 -> 50 | D48: 1 | E48: =D48/C48 -> 0.02
C49: 60 | D49: =E48*C49 -> 1.2 | F49: meaning that in 60 min the PtX can reach 75% of capacity (assumin linear ramping)
D50: Therefore 100%
A51: Notes:
B52: A. For the unit regarding "day" a 100% load factor is assumed here (Where the system is operated at nominal capacity all 24 hours of the day). In operation the daily full load hours may vary and should therefore be adjusted for.
B53: B. Maximum hydrogen output per day, assuming 24 hours of full load operation in a day.
B54: C. The values were derived from multiple sources. 2025 and 2040 were calculated using linear regression based on the data provided in the mentioned references, encompassing the years 2020, 2030, and 2050.
B55: D. Upper and lower values are based on the average of the standard deviations found in the relevant data as shown in note C. Standard deviations for specific investments follow expected values from typical pre-FEED projects (20%).
B56: E. Based on reference [3], the energy consumption of the entire system (including both stack and balance of plant components) is estimated.
B57: F. Efficiency for AEC and PEMEC is calculated based on the electricity consumption of the stack and BOP level, and assuming the LHV of hydrogen. In the case of SOEC, energy supply for steam production is also included.
B58: G. The HHV electrolyser efficiency can be calculated as the sum of the rows: "ΔE from HHV to LHV" and "Hydrogen".
B59: H. The calculation is based on the HHV and LHV of hydrogen.
B60: I. 3% of the energy is estimated to be unrecoverable for AEC and PEMEC hydrogen plants.
B61: J. 50 °C (expected to increase to 70°C, by 2024).
B62: K. Based on internal projects and references performed at Ramboll including FEED projects and estimations from clients and from suppliers.
B63: L. Values have been rounded to nearest 500.
... B77: Z. Weight of stack is assuming wet conditions, where the contrarily to dry conditions, the weight of the electrolyte contributes to the total stack weight.
A80: References:
A81: [4] | B81: [1]. DNV, “Hydrogen Forecast to 2050”, 2022.
A82: [5] | B82: [2]. Monitor Deloitte, “Fueling the Future of Mobility: Hydrogen Electrolysers”, 2021.
A83: [6] | B83: [3]. IRENA, Making the breakthrough: Green hydrogen policies and technology costs, Abu Dhabi, 2021.
A84: [7] | B84: [4]. IEA, “The Future of Hydrogen, Seizing today's opportunities, Executive summary, and recommendations, Report prepared by the IEA for the G20, Japan,” IEA, 2019.
A85: [38] | B85: [5]. DoE Hydrogen and Fuel Cell Technologies Office, “Technical Targets for Proton Exchange Membrane Electrolysis,” DoE, [Accessed July 2023].
A86: [35] | B86: [6]. IRENA, “Green Hydrogen Cost Reduction: Scaling up electrolysers to meet the 1.5°C climate goal,” International Renewable Energy Agency, Abu Dhabi, 2020.
A87: [36] | B87: [7]. IEA, “Global Hydrogen Review 2023,” 2023.
A88: [40] | B88: [8]. Clean Hydrogen Partnership, Strategic Research and Innovation Agenda 2021-2027, 2022.
A89: [22] | B89: [9]. ISPT, “Gigawatt green hydrogen plant; State-of-the-art design and total installed capital costs,” 2020.
A90: [42] | B90: [10]. Fraunhofer Institute for Solar Energy Systems, “COST FORECAST FOR LOW-TEMPERATURE ELECTROLYSIS,” 2021.
A91: [43] | B91: [11]. Janke et.al., “Optimizing power-to-H2 participation in the Nord Pool electricity market: Effects of different bidding strategies on plant operation,” Renewable Energy, vol. 156, pp. 820-836, August 2020.
A92: [44] | B92: [12]. Böhm et.al., “Projecting cost development for future large-scale power-to-gas implementations by scaling effects,” Applied Energy, vol. 264, 15 April 2020.

Sheet AEC
A1: Technology | C1: Assumtions: 100MW produces 45 to 55 ton H2 per day per this sheet. KPI used is 46,6 (2025 ctrl). PtX to convert 100% of captured CO2 to e-Methane needs 37 ton H2 per day. Capactity considering production planning (periodic stop in production due to variation in electrical price and others) we design capacity to be 1.3 times demand of 37 tones per day= 37x1,3=48). | E1: FLH (based on capacity/1,3) | G1: Hydrogen production via alkaline electrolysis (AEC) for 100 MW plant
A2: year | B2: 8200 | C2: PtX (48 of 46,6 ) is set to be the same as 100% (1,3) or a 103MW plant. | E2: =E7/(C7/1000)*24 -> 6015.9829 | G2: 2020 | H2: 2025 | I2: 2030 | J2: 2040 | K2: 2050 | L2: 2020 | M2: 2020 | N2: 2050 | O2: 2050 | P2: Note | Q2: Ref. In doc | R2: Ref
A3: est | C3: 1.03 | D3: Unit | E3: Consumption per year | F3: Unit | G3: ctrl | H3: crtl | I3: ctrl | J3: ctrl | K3: ctrl | L3: Lower | M3: Upper | N3: Lower | O3: Upper | P3: - | Q3: -
A4: cat | B4: par | C4: KPI H2-Production Söndeborg
A5: Energy/technical data
B6: Typical total plant size [MW input_e] | C6: =H6*$C$3 -> 103 | D6: MW | G6: 100 | H6: 100 | I6: 100 | J6: 100 | K6: 100 | L6: 100 | M6: 100 | N6: 100 | O6: 100
B7: Typical total plant size [kgH2 / day of max output] | C7: =C3*H7 -> 48055.988 | D7: Max kg H2/day | E7: 12046 | F7: Tones/year | G7: =(1/G10)*G6*1000*24 -> 45852.469 | H7: =(1/H10)*H6*1000*24 -> 46656.299 | I7: =(1/I10)*I6*1000*24 -> 49378.6 | J7: =(1/J10)*J6*1000*24 -> 51885.161 | K7: =(1/K10)*K6*1000*24 -> 55555.556 | L7: =(1/L10)*L6*1000*24 -> 48191.83 | M7: =(1/M10)*M6*1000*24 -> 43729.712 | N7: =(1/N10)*N6*1000*24 -> 56844.822 | O7: =(1/O10)*O6*1000*24 -> 54323.474 | P7: A, B
B8: Input | C8: Days to reach 12,2 ktons at max prod | D8: =12200/(48056/1000) -> 253.87048
B9: Electricity (% total input [MWh / MWh]) | C9: =H9*$C$3 -> 103 | D9: MW | E9: =C9/1.3*$E$2 -> 476650.95 | F9: MWh | G9: 100 | H9: 100 | I9: 100 | J9: 100 | K9: 100 | L9: 100 | M9: 100 | N9: 100 | O9: 100
B10: Electricity consumption [stack level, KWh/kgH2] | G10: 52.341783 | H10: 51.44 | I10: 48.604052 | J10: 46.256 | K10: 43.2 | L10: 49.800973 | M10: 54.882594 | N10: 42.220204 | O10: 44.179796 | P10: C, D | Q10: [4], [5], [6], [7] | R10: [1], [2], [3], [4]
B11: Electricity consumption [stack+BOP level, KWh/kgH2] | E11: Tech water UPW | G11: 57.685145 | H11: 56.691302 | I11: 53.565843 | J11: 50.978088 | K11: 47.610114 | L11: 54.884953 | M11: 60.485336 | N11: 46.530294 | O11: 48.689933 | P11: E | Q11: [4], [5], [6], [7] | R11: [1], [2], [3], [4]
B12: Ultrapure Water for electrolysis [kg / MWh input_e] | C12: =H12 -> 174.96112 | D12: kg/MWh el | E12: =C12*E9/1000 -> 83395.385 | F12: UPW m3/year | G12: =G20+(G20*8) -> 171.94676 | H12: =H20+(H20*8) -> 174.96112 | I12: =I20+(I20*8) -> 185.16975 | J12: =J20+(J20*8) -> 194.56935 | K12: =K20+(K20*8) -> 208.33333 | L12: =L20+(L20*8) -> 180.71936 | M12: =M20+(M20*8) -> 163.98642 | N12: =N20+(N20*8) -> 213.16808 | O12: =O20+(O20*8) -> 203.71303
B13: UPW for electrolysis m3/h | E13: =E12/$E$2 -> 13.862304 | F13: UPW m3/h
B14: Output | E14: Output
B15: Hydrogen Output (% total input_e [MWh / MWh]) | G15: =(33.3/G11)*100 -> 57.727167 | H15: =(33.3/H11)*100 -> 58.739169 | I15: =(33.3/I11)*100 -> 62.166481 | J15: =(33.3/J11)*100 -> 65.322182 | K15: =(33.3/K11)*100 -> 69.943122 | L15: =(33.3/L11)*100 -> 60.672367 | M15: =(33.3/M11)*100 -> 55.054666 | N15: =(33.3/N11)*100 -> 71.566278 | O15: =(33.3/O11)*100 -> 68.391961 | P15: F
B16: ΔE from HHV to LHV (% total input_e [MWh / MWh]) | G16: =(G20*39.4/1000*100)-(33.3/G10)*100 -> 11.654169 | H16: =(H20*39.4/1000*100)-(33.3/H10)*100 -> 11.858476 | I16: =(I20*39.4/1000*100)-(33.3/I10)*100 -> 12.550394 | J16: =(J20*39.4/1000*100)-(33.3/J10)*100 -> 13.187478 | K16: =(K20*39.4/1000*100)-(33.3/K10)*100 -> 14.12037 | L16: =(L20*39.4/1000*100)-(33.3/L10)*100 -> 12.248757 | M16: =(M20*39.4/1000*100)-(33.3/M10)*100 -> 11.114635 | N16: =(N20*39.4/1000*100)-(33.3/N10)*100 -> 14.448059 | O16: =(O20*39.4/1000*100)-(33.3/O10)*100 -> 13.807216 | P16: G, H
B17: Heat loss (% total input_e [MWh / MWh]) | E17: Heat loss / cooling | G17: =100-G15-G16 -> 30.618663 | H17: =100-H15-H16 -> 29.402355 | I17: =100-I15-I16 -> 25.283124 | J17: =100-J15-J16 -> 21.490339 | K17: =100-K15-K16 -> 15.936508 | L17: =100-L15-L16 -> 27.078877 | M17: =100-M15-M16 -> 33.830699 | N17: =100-N15-N16 -> 13.985663 | O17: =100-O15-O16 -> 17.800823
B18: - hereof unrecoverable heat loss [%-points of heat loss] | C18: =H18/100*C9 -> 3.09 | D18: MW | E18: =C18/1.3*$E$2 -> 14299.529 | F18: MWh | G18: 3 | H18: 3 | I18: 3 | J18: 3 | K18: 3 | L18: 3 | M18: 3 | N18: 3 | O18: 3 | P18: I
B19: - hereof recoverable for district heating [%-points of heat loss] | C19: =H19/100*C9 -> 27.194425 | D19: MW | E19: =C19/1.3*$E$2 -> 125847.08 | F19: MWh | G19: =G17-G18 -> 27.618663 | H19: =H17-H18 -> 26.402355 | I19: =I17-I18 -> 22.283124 | J19: =J17-J18 -> 18.490339 | K19: =K17-K18 -> 12.936508 | L19: =L17-L18 -> 24.078877 | M19: =M17-M18 -> 30.830699 | N19: =N17-N18 -> 10.985663 | O19: =O17-O18 -> 14.800823 | P19: J
B20: Hydrogen [kg / MWh input_e] | E20: =E9*H20 -> 9266153.8 | F20: kg H2 per year | G20: =(G7/24)/G6 -> 19.105195 | H20: =(H7/24)/H6 -> 19.440124 | I20: =(I7/24)/I6 -> 20.574416 | J20: =(J7/24)/J6 -> 21.618817 | K20: =(K7/24)/K6 -> 23.148148 | L20: =(L7/24)/L6 -> 20.079929 | M20: =(M7/24)/M6 -> 18.220713 | N20: =(N7/24)/N6 -> 23.685343 | O20: =(O7/24)/O6 -> 22.634781
B21: Forced outage [%] | G21: 3 | H21: 3 | I21: 3 | J21: 3 | K21: 3 | L21: 3 | M21: 3 | N21: 3 | O21: 3 | P21: K
B22: Planned outage [days per year] | G22: 11 | H22: 11 | I22: 11 | J22: 11 | K22: 11 | L22: 11 | M22: 11 | N22: 11 | O22: 11 | P22: K
B23: Technical lifetime [years] | G23: 25 | H23: 25 | I23: 25 | J23: 25 | K23: 25 | L23: 20 | M23: 30 | N23: 20 | O23: 30 | P23: K
B24: Frequency of stack replacement [h] | C24: 2 month | G24: 70000 | H24: 80000 | I24: 92500 | J24: 94500 | K24: 101500 | L24: 61500 | M24: 78500 | N24: 83000 | O24: 120000 | P24: C, D, L | Q24: [4], [5], [6], [7], [37] | R24: [1], [2], [3], [4], [5]
B25: Construction time [years] | G25: 2 | H25: 2 | I25: 2 | J25: 2 | K25: 2 | L25: 1.5 | M25: 2 | N25: 1.5 | O25: 2 | P25: M
A26: Financial data (2020 price level) | E26: CAPEX | F26: Euros k€
B27: Specific investment [€ / kW of total input_e] | C27: =H27 -> 875 | E27: =C27*C9 -> 90125 | F27: k€ | G27: 1200 | H27: 875 | I27: 550 | J27: 425 | K27: 300 | L27: 950 | M27: 1450 | N27: 250 | O27: 350 | P27: D, N, O | Q27: [5], [37], [35], [36], [40], [41], [42] | R27: [2], [4], [5], [6], [7], [8], [9], [10]
B28: - hereof electrolyser stack [€ / kW of total input_e] | C28: =H28 -> 183.67012 | G28: =G$27*20.9908709397468% -> 251.89045 | H28: =H$27*20.9908709397468% -> 183.67012 | I28: =I$27*20.9908709397468% -> 115.44979 | J28: =J$27*20.9908709397468% -> 89.211201 | K28: =K$27*20.9908709397468% -> 62.972613 | L28: =L$27*20.9908709397468% -> 199.41327 | M28: =M$27*20.9908709397468% -> 304.36763 | N28: =N$27*20.9908709397468% -> 52.477177 | O28: =O$27*20.9908709397468% -> 73.468048 | P28: P, Q
B29: - hereof electrolyser system [€ / kW of total input_e] | C29: =H29 -> 393.72008 | G29: =G$27*44.9965808962557% -> 539.95897 | H29: =H$27*44.9965808962557% -> 393.72008 | I29: =I$27*44.9965808962557% -> 247.48119 | J29: =J$27*44.9965808962557% -> 191.23547 | K29: =K$27*44.9965808962557% -> 134.98974 | L29: =L$27*44.9965808962557% -> 427.46752 | M29: =M$27*44.9965808962557% -> 652.45042 | N29: =N$27*44.9965808962557% -> 112.49145 | O29: =O$27*44.9965808962557% -> 157.48803 | P29: P, Q
B30: - hereof BOP [€ / kW of total input_e] | C30: =H30 -> 115.59332 | G30: =G$27*13.2106654486895% -> 158.52799 | H30: =H$27*13.2106654486895% -> 115.59332 | I30: =I$27*13.2106654486895% -> 72.65866 | J30: =J$27*13.2106654486895% -> 56.145328 | K30: =K$27*13.2106654486895% -> 39.631996 | L30: =L$27*13.2106654486895% -> 125.50132 | M30: =M$27*13.2106654486895% -> 191.55465 | N30: =N$27*13.2106654486895% -> 33.026664 | O30: =O$27*13.2106654486895% -> 46.237329 | P30: P, Q
B31: - hereof Control System [€ / kW of total input_e] | C31: =H31 -> 56.335425 | G31: =G$27*6.43833433130981% -> 77.260012 | H31: =H$27*6.43833433130981% -> 56.335425 | I31: =I$27*6.43833433130981% -> 35.410839 | J31: =J$27*6.43833433130981% -> 27.362921 | K31: =K$27*6.43833433130981% -> 19.315003 | L31: =L$27*6.43833433130981% -> 61.164176 | M31: =M$27*6.43833433130981% -> 93.355848 | N31: =N$27*6.43833433130981% -> 16.095836 | O31: =O$27*6.43833433130981% -> 22.53417 | P31: P, Q
B32: - hereof Civil Infrastructure [€ / kW of total input_e] | C32: =H32 -> 28.458826 | G32: =G$27*3.25243727288709% -> 39.029247 | H32: =H$27*3.25243727288709% -> 28.458826 | I32: =I$27*3.25243727288709% -> 17.888405 | J32: =J$27*3.25243727288709% -> 13.822858 | K32: =K$27*3.25243727288709% -> 9.7573118 | L32: =L$27*3.25243727288709% -> 30.898154 | M32: =M$27*3.25243727288709% -> 47.16034 | N32: =N$27*3.25243727288709% -> 8.1310932 | O32: =O$27*3.25243727288709% -> 11.38353 | P32: P, Q
B33: - hereof Indirects [€ / kW of total input_e] | C33: =H33 -> 97.222222 | G33: =G$27*11.1111111111111% -> 133.33333 | H33: =H$27*11.1111111111111% -> 97.222222 | I33: =I$27*11.1111111111111% -> 61.111111 | J33: =J$27*11.1111111111111% -> 47.222222 | K33: =K$27*11.1111111111111% -> 33.333333 | L33: =L$27*11.1111111111111% -> 105.55556 | M33: =M$27*11.1111111111111% -> 161.11111 | N33: =N$27*11.1111111111111% -> 27.777778 | O33: =O$27*11.1111111111111% -> 38.888889 | P33: P, Q
B34: Specific investment [€ / kgH2 / day of max output] | C34: =H34 -> 1875.4167 | E34: =C34*C7 -> 90125000 | F34: Contol -ok (same as cell E27) | G34: =G27/(G7/1000/G6) -> 2617.0892 | H34: =H27/(H7/1000/H6) -> 1875.4167 | I34: =I27/(I7/1000/I6) -> 1113.8428 | J34: =J27/(J7/1000/J6) -> 819.11667 | K34: =K27/(K7/1000/K6) -> 540 | L34: =L27/(L7/1000/L6) -> 1971.2885 | M34: =M27/(M7/1000/M6) -> 3315.8234 | N34: =N27/(N7/1000/N6) -> 439.79379 | O34: =O27/(O7/1000/O6) -> 644.28869 | P34: A, B, P
B35: - hereof equipment [%] | C35: =H35 -> 90 | G35: 90 | H35: 90 | I35: 90 | J35: 90 | K35: 90 | L35: 90 | M35: 90 | N35: 90 | O35: 90 | P35: K, R
B36: - hereof installation [%] | C36: =H36 -> 10 | E36: OPEX Fixed | G36: 10 | H36: 10 | I36: 10 | J36: 10 | K36: 10 | L36: 10 | M36: 10 | N36: 10 | O36: 10 | P36: K, R
B37: Fixed O&M [% of specific investment / year] | C37: =H37 -> 4 | E37: =H37/100*E27 -> 3605 | F37: k€/year | G37: 4 | H37: 4 | I37: 4 | J37: 4 | K37: 4 | L37: 4 | M37: 4 | N37: 4 | O37: 4 | P37: K, S | Q37: [40] | R37: [8]
B38: Variable O&M [€ / kWh of total input] | C38: Use data from othe H2 production plant | G38: - | H38: - | I38: - | J38: - | K38: - | P38: T
A39: Technology specific data
B40: Current Density [A / cm2] | G40: 0.6 | H40: 0.8 | I40: 1 | J40: 1.2 | K40: 1.5 | L40: 0.4 | M40: 0.6 | N40: 1.2 | O40: 1.5 | P40: K, U | Q40: [40] | R40: [8]
B41: Flexibility
B42: - cold start up time [min from 0 to 100%] | G42: 80 | H42: 60.416667 | I42: 30 | J42: <30 | K42: <30 | L42: 49.896036 | M42: 105 | N42: <30 | O42: <30 | P42: V | Q42: [6], [40], [43] | R42: [3], [8], [11]
B43: Stack size [MW] | G43: 2 | H43: 5 | I43: 5 | J43: 10 | K43: 10 | L43: 1.5 | M43: 2.5 | N43: 10 | O43: 10 | Q43: [6], [42], [44] | R43: [3], [10], [12]
B44: Degradation rate [% / 1000 h] | G44: 0.145 | H44: 0.13 | I44: 0.115 | J44: 0.11 | K44: 0.1 | L44: 0.12458759 | M44: 0.16541241 | N44: 0.11064996 | O44: 0.089350045 | P44: K, U, W | Q44: [37], [40] | R44: [5], [8]
B45: Electrolyser Unit [m2/MW] | E45: Area | G45: 25 | H45: 21.276596 | I45: 12.5 | J45: 10.37234 | K45: 8.2978723 | L45: 37.5 | M45: 18.75 | N45: 12.446809 | O45: 6.2234043 | P45: X
B46: Plant Footprint [m2 / MW input_e] | C46: =H46 -> 183.82979 | D46: m2 | E46: =C46*C9 -> 18934.468 | F46: m2 | G46: 216 | H46: 183.82979 | I46: 108 | J46: 89.617021 | K46: 71.693617 | L46: 172.8 | M46: 324 | N46: 57.354894 | O46: 107.54043 | P46: X, Y
B47: Weight of Electrolyser Stack [MW/tons] | G47: 24 | H47: 18 | I47: 14.4 | J47: 12 | K47: 9.6 | L47: 16 | M47: 24 | N47: 7.68 | O47: 9.6 | P47: K, Z
C49: =7.46*E27 -> 672332.5
A52: Notes:
B53: A. For the unit regarding "day" a 100% load factor is assumed here (Where the system is operated at nominal capacity all 24 hours of the day). In operation the daily full load hours may vary and should therefore be adjusted for.
B54: B. Maximum hydrogen output per day, assuming 24 hours of full load operation in a day.
B55: C. The values were derived from multiple sources. 2025 and 2040 were calculated using linear regression based on the data provided in the mentioned references, encompassing the years 2020, 2030, and 2050.
B56: D. Upper and lower values are based on the average of the standard deviations found in the relevant data as shown in note C. Standard deviations for specific investments follow expected values from typical pre-FEED projects (20%).
B57: E. Based on reference [3], the energy consumption of the entire system (including both stack and balance of plant components) is estimated.
B58: F. Efficiency for AEC and PEMEC is calculated based on the electricity consumption of the stack and BOP level, and assuming the LHV of hydrogen. In the case of SOEC, energy supply for steam production is also included.
B59: G. The HHV electrolyser efficiency can be calculated as the sum of the rows: "ΔE from HHV to LHV" and "Hydrogen".
B60: H. The calculation is based on the HHV and LHV of hydrogen.
B61: I. 3% of the energy is estimated to be unrecoverable for AEC and PEMEC hydrogen plants.
B62: J. 50 °C (expected to increase to 70°C, by 2024).
B63: K. Based on internal projects and references performed at Ramboll including FEED projects and estimations from clients and from suppliers.
B64: L. Values have been rounded to nearest 500.
... B78: Z. Weight of stack is assuming wet conditions, where the contrarily to dry conditions, the weight of the electrolyte contributes to the total stack weight.
A81: References:
A82: [4] | B82: [1]. DNV, “Hydrogen Forecast to 2050”, 2022.
A83: [5] | B83: [2]. Monitor Deloitte, “Fueling the Future of Mobility: Hydrogen Electrolysers”, 2021.
A84: [6] | B84: [3]. IRENA, Making the breakthrough: Green hydrogen policies and technology costs, Abu Dhabi, 2021.
A85: [7] | B85: [4]. IEA, “The Future of Hydrogen, Seizing today's opportunities, Executive summary, and recommendations, Report prepared by the IEA for the G20, Japan,” IEA, 2019.
A86: [37] | B86: [5]. DoE Hydrogen and Fuel Cell Technologies Office, “Technical Targets for Liquid Alkaline Electrolysis,” DoE, [Accessed July 2023].
A87: [35] | B87: [6]. IRENA, “Green Hydrogen Cost Reduction: Scaling up electrolysers to meet the 1.5°C climate goal,” International Renewable Energy Agency, Abu Dhabi, 2020.
A88: [36] | B88: [7]. IEA, “Global Hydrogen Review 2023,” 2023.
A89: [40] | B89: [8]. Clean Hydrogen Partnership, Strategic Research and Innovation Agenda 2021-2027, 2022.
A90: [41] | B90: [9]. ISPT, “Gigawatt green hydrogen plant; State-of-the-art design and total installed capital costs,” 2020.
A91: [42] | B91: [10]. Fraunhofer Institute for Solar Energy Systems, “COST FORECAST FOR LOW-TEMPERATURE ELECTROLYSIS,” 2021.
A92: [43] | B92: [11]. Janke et.al., “Optimizing power-to-H2 participation in the Nord Pool electricity market: Effects of different bidding strategies on plant operation,” Renewable Energy, vol. 156, pp. 820-836, August 2020.
A93: [44] | B93: [12]. Böhm et.al., “Projecting cost development for future large-scale power-to-gas implementations by scaling effects,” Applied Energy, vol. 264, 15 April 2020.

Sheet Water qualities
A1: Temperature | B1: Pressure (p) | C1: Density (Rho) | D1: Specific heat (Cp) | E1: Kinematic viscosity
A2: °C | B2: Pa | C2: kg/m3 | D2: kj/kg.K | E2: m²/s
A3: 0 | B3: 101325 | C3: 999.82 | D3: 4.217 | E3: 1.7923226e-06
A4: 1 | B4: 101325 | C4: 999.89 | D4: 4.213 | E4: 1.7311904e-06
A5: 2 | B5: 101325 | C5: 999.94 | D5: 4.21 | E5: 1.6741004e-06
A6: 3 | B6: 101325 | C6: 999.98 | D6: 4.207 | E6: 1.6200324e-06
A7: 4 | B7: 101325 | C7: 1000 | D7: 4.205 | E7: 1.569e-06
A8: 5 | B8: 101325 | C8: 1000 | D8: 4.202 | E8: 1.52e-06
A9: 6 | B9: 101325 | C9: 999.99 | D9: 4.2 | E9: 1.4730147e-06
A10: 7 | B10: 101325 | C10: 999.96 | D10: 4.198 | E10: 1.4290572e-06
A11: 8 | B11: 101325 | C11: 999.91 | D11: 4.196 | E11: 1.3861248e-06
A12: 9 | B12: 101325 | C12: 999.85 | D12: 4.194 | E12: 1.3462019e-06
A13: 10 | B13: 101325 | C13: 999.77 | D13: 4.192 | E13: 1.3083009e-06
A14: 11 | B14: 101325 | C14: 999.68 | D14: 4.191 | E14: 1.2714069e-06
... A103: 100 | B103: 101325 | C103: 958.05 | D103: 4.216 | E103: 2.9434789e-07

Sheet Technical temp calculations
D2: known values | K2: We need to calcualte the bossing of Temp when sending to DH so, we can use the HEX but we are missing an upgrading unit in the calcualtions | V2: Step1
D3: calcualted | V3: m_PtH2_1 | W3: Q_ex_PtH2
D4: referemce cells
Y7: 3185.9817 | AA7: 3185.9817
O8: Step3 | S8: Step2
O9: Q_Boosting_heat_PtH2_1 | S9: m_DH_PtH2_1 | V9: =Y9 -> 1885.5548 | W9: kg/s | Y9: =V11*1000/((V10-Y10)*F29) -> 1885.5548 | Z9: kg/s
M10: Tcout | P10: Thin | S10: Thin | V10: 65 | W10: C | X10: Excess heat temp | Y10: 30 | Z10: C
C11: Inputs | M11: =P11 -> 819.25243 | N11: kg/s | P11: =S11 -> 819.25243 | Q11: kg/s | S11: =S13*1000/((S12-Y10)*F29) -> 819.25243 | T11: kg/s | V11: ='Technical temp calculations (2)'!X11 -> 276.18663 | W11: MW | X11: Excess heating CAP | Y11: =Y33 -> 190.47235 | Z11: MW | AA11: Capaciteten er kendt
M12: 90 | N12: C | P12: =S12 -> 65 | Q12: C | S12: =V10 -> 65 | T12: C | AA12: Vi kender i princippet varme capaciteten | AJ12: kg/s
A13: Summer | C13: Time of year | F13: Summer | L13: =M13-S23 -> 171.42857 | M13: =O18+P13 -> 205.71429 | N13: MW | P13: =S13 -> 120 | Q13: MW | R13: =S11*F29*(S12-S22)/1000 -> 85.714286 | S13: 120 | T13: MW | V13: 0.225 | Y13: 40 | AJ13: C | AM13: kg/s
A14: Winter | C14: Cooling capacity | F14: 800 | G14: MW | L14: Q_net_util_heat | M14: Q_util_heat | R14: =S13-R13 -> 34.285714 | S14: Q_ex_PtX_To_DH | AM14: C
V15: Step 4 | W15: Flow_Split | Y15: 40 | Z15: 30
C16: Excess heat temperature | F16: 60 | G16: C | S16: =S11*F29*(S12-S22)/1000 -> 85.714286 | V16: =V9-S11 -> 1066.3023 | W16: kg/s
C17: Cooling temperature | F17: 30 | G17: C | L17: =O18+R13 -> 171.42857 | M17: =O18*1000/((M12-P12)*F29) -> 819.25243 | V17: =V10 -> 65 | W17: C | Y17: =V9*F29*(Y15-Z15)/1000 -> 78.910467 | AJ17: kg/s
C18: Seawater | O18: =S11*F29*(M12-P12)/1000 -> 85.714286 | P18: MW | Q18: Q_boost_PtH2 | V18: =V16*F29*(V17-Y10)/1000 -> 156.18663 | W18: MW | X18: Q_Flow_Split | AJ18: C
C19: Summer temp | F19: 25 | G19: C | Y19: The value below when substrated from each other is the value that remains
C20: Winter temp | F20: 0 | G20: C | W20: m_Mixing_PtH2_1 | Y20: in the return thermal energy and thereby the thermal energy that cannot be utilized in the DH system | AM20: kg/s
C21: Density | F21: 1.022 | G21: kg/L | L21: dh | M21: 175 | S21: =S11 -> 819.25243 | T21: kg/s | V21: =S21+V16 -> 1885.5548 | W21: kg/s | Y21: =V18 -> 156.18663 | Z21: =V23 -> 190.47235 | AM21: C
C22: Cp | F22: 4.002 | G22: kJ/ kg K | L22: WTE | M22: 50 | S22: =F30 -> 40 | T22: C | V22: =(S21*F29*S22+V16*F29*V17)/(V16*F29+S21*F29) -> 54.13778 | W22: C
C23: dT | F23: 10 | G23: k | K23: Q_Available_Heat | L23: Avaliable heat | M23: =M21-M22 -> 125 | S23: =V23-V18 -> 34.285714 | T23: MW | V23: =V21*F29*(V22-Y10)/1000 -> 190.47235 | W23: MW | X23: Q_Mixing_PtH2_1
S24: ThOut
S25: Q_Unutil_heat
C26: DH | S26: =V23-V18 -> 34.285714 | T26: =V18+S23 -> 190.47235
C27: Required DH temperature | F27: 68 | G27: C | S27: =S21*F29*(S22-Y10)/1000 -> 34.285714
C28: Density | F28: 983.13 | M28: 1051.374
C29: Cp | F29: 4.185 | G29: kJ/ kg K
C30: Return | F30: 40 | G30: C | M30: 20
C31: Density | F31: 992.25 | M31: 20 | R31: Thin | S31: =V21 -> 1885.5548 | T31: kg/s | Y31: =Y9 -> 1885.5548 | Z31: kg/s | AA31: ThOut
B32: 813.59177 | C32: Cp | F32: 4.179 | M32: 20 | S32: =V22 -> 54.13778 | T32: C | Y32: =Y10 -> 30 | Z32: C | AA32: We know this value as it is the dimension value for the HEX, being the demanded temperature
B33: 1500 | C33: Mass flow | D33: DH HEX | F33: 1750 | G33: kg/s | M33: 50 | P33: Step 7 Q_Cooling_PtH2_1 | R33: We know that CAP of HEX as it should be able to cooled every think away | S33: =F29*S31*(S32-Y32)/1000 -> 190.47235 | T33: MW | Y33: =S33 -> 190.47235 | Z33: MW
C34: DH capacity | F34: 200 | G34: MW
R37: Tcout | S37: =Y37 -> 4759.429 | T37: kg/s | Y37: =Y39/((S44-Y38)*F22)*1000 -> 4759.429 | Z37: kg/s | AA37: Tcin
S38: =((S31*F29*(S32-Y32))/(Y37*F22))+Y38 -> 35 | T38: C | Y38: 25 | Z38: C
S39: =S33 -> 190.47235 | T39: MW | Y39: =S33 -> 190.47235 | Z39: MW
S40: =F32*S37*(S38-Y38)/1000 -> 198.89654
AA42: We know the inputs of cooling, e.g. we know the sea water temp or chiller's technical dimenstions
C43: DC | S43: =Y37 -> 4759.429 | T43: kg/s
C44: Forward temp | F44: 10 | S44: =Y38+F23 -> 35 | T44: C | AA44: So we know that the Sea water is 25C
C45: Density | F45: 999.77 | S45: =S33 -> 190.47235 | T45: MW | AA45: The capacity varies depending on the needs, so do the heating sector take some or not. Therefore this number referece to the input of the HEX
C46: Cp | F46: 4.192
C47: Return | F47: 16
C48: Density | F48: 999.03
C49: Cp | F49: 4.185
V54: =1000*Cockpit!AS8*(70-30) -> 167.4

Sheet Technical temp calculations (2)
D2: known values | K2: We need to calcualte the bossing of Temp when sending to DH so, we can use the HEX but we are missing an upgrading unit in the calcualtions | X2: Step1
D3: calcualted | X3: m_PtH2_1 | Y3: Q_ex_PtH2
D4: referemce cells | AC4: =X9+AF9 -> 4646.1128
AA7: 3185.9817 | AC7: =AF9=AA9 -> FALSE
O8: Step3 | U8: Step2
O9: Q_Boosting_heat_PtH2_1 | U9: m_DH_PtH2_1 | X9: =AA9 -> 2639.7767 | Y9: kg/s | AA9: =X11*1000/((X10-AA10)*F29) -> 2639.7767 | AB9: kg/s | AC9: =AA9+AF9 -> 4646.1128 | AF9: =AI9 -> 2006.3361 | AG9: kg/s | AI9: =AF11*1000/((AF10-AI10)*F29) -> 2006.3361 | AJ9: kg/s
M10: Tcout | P10: Thin | U10: Thin | X10: 60 | Y10: C | Z10: Excess heat temp | AA10: 35 | AB10: C | AF10: 70 | AG10: C | AH10: Excess heat temp | AI10: 30 | AJ10: C
C11: Inputs | M11: =P11 -> 0 | N11: kg/s | P11: =U11 -> 0 | Q11: kg/s | U11: =X13+X14 -> 0 | V11: kg/s | X11: =Cockpit!AF3*Cockpit!AF5 -> 276.18663 | Y11: MW | Z11: Excess heating CAP | AA11: =X11 -> 276.18663 | AB11: MW | AC11: Capaciteten er kendt | AF11: =Cockpit!AJ3*Cockpit!AJ5 -> 335.86067 | AG11: MW | AH11: Excess heating CAP | AI11: =AF11 -> 335.86067 | AJ11: MW
M12: 90 | N12: C | P12: =U12 -> #DIV/0! | Q12: C | U12: =(X14*F29*AF10+X13*F29*X10)/(X13*F29+X14*F29) -> #DIV/0! | V12: C | AC12: Vi kender i princippet varme capaciteten | AQ12: kg/s
A13: Summer | C13: Time of year | F13: Summer | M13: =O18+P13 -> #DIV/0! | N13: MW | P13: =U13 -> #DIV/0! | Q13: MW | U13: =U11*F29*(U12-U22)/1000 -> #DIV/0! | V13: MW | X13: =X9*Z13 -> 0 | Y13: =X9-X13 -> 2639.7767 | Z13: 0 | AQ13: C | AT13: kg/s
A14: Winter | C14: Cooling capacity | F14: 800 | G14: MW | L14: Q_net_util_heat | M14: Q_util_heat | U14: Q_ex_PtX_To_DH | X14: =Z14*AF9 -> 0 | Y14: =AF9-X14 -> 2006.3361 | Z14: 0 | AT14: C
X15: Step 4 | Y15: Flow_Split
C16: Excess heat temperature | F16: 60 | G16: C | U16: =U12=X17 -> #DIV/0! | X16: =Y13+Y14 -> 4646.1128 | Y16: kg/s
C17: Cooling temperature | F17: 30 | G17: C | M17: =O18*1000/((M12-P12)*F29) -> #DIV/0! | X17: =(Y14*F29*AF10+Y13*F29*X10)/(Y13*F29+Y14*F29) -> 64.318311 | Y17: C | AQ17: kg/s
C18: Seawater | O18: =U11*F29*(M12-P12)/1000 -> #DIV/0! | P18: MW | Q18: Q_boost_PtH2 | X18: =X16*F29*(X17-AA10)/1000 -> 570.06472 | Y18: MW | Z18: Q_Flow_Split | AQ18: C
C19: Summer temp | F19: 25 | G19: C | AA19: The value below when substrated from each other is the value that remains
C20: Winter temp | F20: 0 | G20: C | Y20: m_Mixing_PtH2_1 | AA20: in the return thermal energy and thereby the thermal energy that cannot be utilized in the DH system | AT20: kg/s
C21: Density | F21: 1.022 | G21: kg/L | L21: dh | M21: 175 | O21: =P21*1000/(F29*(M12-P12)) -> #DIV/0! | P21: 20 | U21: =U11 -> 0 | V21: kg/s | X21: =U21+X16 -> 4646.1128 | Y21: kg/s | Z21: =(X9+AF9)=X21 -> TRUE | AA21: =X18 -> 570.06472 | AB21: =X23 -> 667.28463 | AT21: C
C22: Cp | F22: 4.002 | G22: kJ/ kg K | L22: WTE | M22: 50 | O22: =P22*1000/(F29*(M12-P12)) -> #DIV/0! | P22: 50 | U22: =F30 -> 40 | V22: C | X22: =(U21*F29*U22+X16*F29*X17)/(X16*F29+U21*F29) -> 64.318311 | Y22: C
C23: dT | F23: 10 | G23: k | K23: Q_Available_Heat | L23: Avaliable heat | M23: =M21-M22 -> 125 | O23: =SUM(O21:O22) -> #DIV/0! | P23: =SUM(P21:P22) -> 70 | Q23: =O23=P11 -> #DIV/0! | U23: =X23-X18 -> 97.219911 | V23: MW | X23: =X21*F29*(X22-AI10)/1000 -> 667.28463 | Y23: MW | Z23: Q_Mixing_PtH2_1
O24: 836.32019 | U24: ThOut
U25: Q_Unutil_heat
C26: DH | U26: =X23-X18 -> 97.219911 | V26: =X18+U23 -> 667.28463
C27: Required DH temperature | F27: 68 | G27: C | U27: =U21*F29*(U22-AI10)/1000 -> 0
C28: Density | F28: 983.13
C29: Cp | F29: 4.185
C30: Return | F30: 40 | G30: C
C31: Density | F31: 992.25 | T31: Thin | U31: =X9 -> 2639.7767 | V31: kg/s | AA31: =AA9 -> 2639.7767 | AB31: kg/s
B32: 813.59177 | C32: Cp | U32: =X22 -> 64.318311 | V32: C | AA32: =AA10 -> 35 | AB32: C | AF32: =AF9 -> 2006.3361 | AG32: kg/s | AL32: =AI9 -> 2006.3361 | AM32: kg/s
B33: 1500 | C33: Mass flow | D33: DH HEX | F33: 1750 | G33: kg/s | P33: Step 7 Q_Cooling_PtH2_1 | T33: We know that CAP of HEX as it should be able to cooled every think away | U33: =F29*U31*(U32-AA32)/1000 -> 323.89303 | V33: MW | AA33: =U33 -> 323.89303 | AB33: MW | AF33: =X22 -> 64.318311 | AG33: C | AL33: =AI10 -> 30 | AM33: C
C34: DH capacity | F34: 200 | G34: MW | AF34: =F29*AF32*(AF33-AL33)/1000 -> 288.15428 | AG34: MW | AL34: =AF34 -> 288.15428 | AM34: MW
T37: Tcout | U37: =AA37 -> 8093.2791 | V37: kg/s | AA37: =AA39/((U44-AA38)*F22)*1000 -> 8093.2791 | AB37: kg/s
U38: =((U31*F29*(U32-AA32))/(AA37*F22))+AA38 -> 35 | V38: C | AA38: {=_xlfn.IFS(F13=A13,F19,F13=A14,F20)} -> 25 | AB38: C | AF38: =AL38 -> 7200.2568 | AG38: kg/s | AL38: =AL40/((U44-AL39)*F22)*1000 -> 7200.2568 | AM38: kg/s
U39: =U33 -> 323.89303 | V39: MW | AA39: =U33 -> 323.89303 | AB39: MW | AF39: =((AF32*R30*(AF33-AL33))/(AL38*F22))+AL39 -> 25 | AG39: C | AL39: {=_xlfn.IFS(F13=A13,F19,F13=A14,F20)} -> 25 | AM39: C
U40: =F32*U37*(U38-AA38)/1000 -> 0 | AF40: =AF34 -> 288.15428 | AG40: MW | AL40: =AF34 -> 288.15428 | AM40: MW
AF41: =AF34*AF38*(AF39-AL39)/1000 -> 0
C43: DC | U43: =AA37 -> 8093.2791 | V43: kg/s
C44: Forward temp | F44: 10 | U44: =AA38+F23 -> 35 | V44: C
C45: Density | F45: 999.77 | U45: =U33 -> 323.89303 | V45: MW
C46: Cp | F46: 4.192
C47: Return | F47: 16
C48: Density | F48: 999.03
C49: Cp | F49: 4.185
X54: =1000*Cockpit!AS8*(70-30) -> 167.4
O77: stream 1 | P77: stream 2 | Q77: Fmix | Z77: DH Strem | AA77: Flow mix | AB77: F_dc
M78: 60 | O78: 60 | P78: 70 | Q78: 0 | T78: 0.25 | U78: 0.5 | V78: 0.75 | W78: 1 | Z78: 40 | AA78: =U82 -> 65 | AB78: 0 | AC78: 0.25 | AD78: 0.5 | AE78: 0.75 | AF78: 1
Q79: =$M$78+(Q78*($P$78-$O$78)) -> 60 | T79: =$O$78+(T78*($P$78-$O$78)) -> 62.5 | U79: =$O$78+(U78*($P$78-$O$78)) -> 65 | V79: =$O$78+(V78*($P$78-$O$78)) -> 67.5 | W79: =$O$78+(W78*($P$78-$O$78)) -> 70 | AB79: =$Z$78+(AB78*($AA$78-$Z$78)) -> 40 | AC79: =$Z$78+(AC78*($AA$78-$Z$78)) -> 46.25 | AD79: =$Z$78+(AD78*($AA$78-$Z$78)) -> 52.5 | AE79: =$Z$78+(AE78*($AA$78-$Z$78)) -> 58.75 | AF79: =$Z$78+(AF78*($AA$78-$Z$78)) -> 65
O80: 60 | P80: 70 | Q80: F_dc
Q81: 0 | T81: 0.25 | U81: 0.5 | V81: 0.75 | W81: 1
Q82: =$O$80+(Q81*($P$80-$O$80)) -> 60 | T82: =$O$78+(T81*($P$78-$O$78)) -> 62.5 | U82: =$O$78+(U81*($P$78-$O$78)) -> 65 | V82: =$O$78+(V81*($P$78-$O$78)) -> 67.5 | W82: =$O$78+(W81*($P$78-$O$78)) -> 70

Sheet Data Wind Energinet
A1: HourDK | B1: PriceArea | C1: Solar - ForecastCurrent MWh/h | D1: Onshore Wind - ForecastCurrent MWh/h | E1: Offshore Wind - ForecastCurrent MWh/h | F1: Samlet | G1: Samlet wind
A2: 44927 | B2: DK1 | C2: 0.015 | D2: 471.58334 | E2: 118.79166 | F2: =E2+D2+C2 -> 590.39001 | G2: =E2+D2 -> 590.37501
A3: 44927.042 | B3: DK1 | C3: 0 | D3: 697.875 | E3: 190.29167 | F3: =E3+D3+C3 -> 888.16667 | G3: =E3+D3 -> 888.16667
A4: 44927.083 | B4: DK1 | C4: 0 | D4: 881.45831 | E4: 284.625 | F4: =E4+D4+C4 -> 1166.0833 | G4: =E4+D4 -> 1166.0833
A5: 44927.125 | B5: DK1 | C5: 0 | D5: 861.41669 | E5: 306.33334 | F5: =E5+D5+C5 -> 1167.75 | G5: =E5+D5 -> 1167.75
A6: 44927.167 | B6: DK1 | C6: 0.000417 | D6: 916.875 | E6: 343.95834 | F6: =E6+D6+C6 -> 1260.8338 | G6: =E6+D6 -> 1260.8333
A7: 44927.208 | B7: DK1 | C7: 0.012083 | D7: 987.70831 | E7: 396.58334 | F7: =E7+D7+C7 -> 1384.3037 | G7: =E7+D7 -> 1384.2917
A8: 44927.25 | B8: DK1 | C8: 0.02375 | D8: 846.625 | E8: 197.95833 | F8: =E8+D8+C8 -> 1044.6071 | G8: =E8+D8 -> 1044.5833
A9: 44927.292 | B9: DK1 | C9: 0.035417 | D9: 966.16669 | E9: 199.41667 | F9: =E9+D9+C9 -> 1165.6188 | G9: =E9+D9 -> 1165.5834
A10: 44927.333 | B10: DK1 | C10: 0.129583 | D10: 1399.625 | E10: 277.04166 | F10: =E10+D10+C10 -> 1676.7962 | G10: =E10+D10 -> 1676.6667
A11: 44927.375 | B11: DK1 | C11: 7.9725 | D11: 1698.3334 | E11: 340.54166 | F11: =E11+D11+C11 -> 2046.8475 | G11: =E11+D11 -> 2038.875
A12: 44927.417 | B12: DK1 | C12: 27.239584 | D12: 1760.7916 | E12: 593.45831 | F12: =E12+D12+C12 -> 2381.4895 | G12: =E12+D12 -> 2354.2499
A13: 44927.458 | B13: DK1 | C13: 66.359581 | D13: 2148.3333 | E13: 757.45831 | F13: =E13+D13+C13 -> 2972.1511 | G13: =E13+D13 -> 2905.7916
... A8761: 45291.958 | B8761: DK1 | C8761: 0 | D8761: 1501 | E8761: 1000.2917 | F8761: =E8761+D8761+C8761 -> 2501.2917 | G8761: =E8761+D8761 -> 2501.2917

Sheet TO DO
A1: Technology | B1: To DO
A2: PtX | B2: Water C_p should vary depending on the water temperaute
A3: DH and DC input | B3: DH return temp and ambiant cooling temp should very doing the year
A4: Cooling sector | B4: Make a cooling sector having cooling tower, Seawater cooling with HEX and chiller This python code should be generic, so that e.g. a PtX can call one of these technologies an utilitze is how they see it fit for their energy system. By doing this you do not have to model the PtX cooling system individually
A5: Cooling / heating sector | B5: Make a heat pump which can make cooling and heating
A6: PtX | B6: missing variable OPEX
A7: WTE | B7: kører først uanset pris
A8: Boilers | B8: All the Boilers and everything else, please ensure that the code are listing the def rule as constriants
A9: Start up cost | B9: I think that this should be a == and not =<
A10: Generel check | B10: Check that the constraints are right, so sometimes you could have used == instead of <= or >=
A11: General | B11: Changes the names so that it starts with the name of the technology, so Q_WTE is WTE_Q
A12: Start cost | B12: Start cost is now >= but it should be ==
... A15: Solar panel | B15: Need to understand if you can curtail an SP, because if you cannot then the first equation should not be <= but ==
